{
  "dates": [],
  "campgrounds": [],
  "campground_dates": [
    {
      "campground": "new_brigthon_sb",
      "dates": [
        {
          "date": "08/22/2024_08/25/2024",
          "spotsAvailable": 0,
          "lastUpdated": "8/23/2024 12:02:52 AM"
        },
        {
          "date": "08/29/2024_09/01/2024",
          "spotsAvailable": 0,
          "lastUpdated": "8/30/2024 12:06:30 AM"
        },
        {
          "date": "09/05/2024_09/08/2024",
          "spotsAvailable": 0,
          "lastUpdated": "9/5/2024 7:02:48 PM"
        },
        {
          "date": "09/12/2024_09/15/2024",
          "spotsAvailable": 0,
          "lastUpdated": "9/9/2024 3:09:31 AM"
        },
        {
          "date": "09/19/2024_09/22/2024",
          "spotsAvailable": 0,
          "lastUpdated": "9/9/2024 3:09:38 AM"
        },
        {
          "date": "09/26/2024_09/29/2024",
          "spotsAvailable": 0,
          "lastUpdated": "9/9/2024 3:09:45 AM"
        },
        {
          "date": "10/03/2024_10/06/2024",
          "spotsAvailable": 0,
          "lastUpdated": "9/9/2024 3:09:52 AM"
        },
        {
          "date": "10/10/2024_10/13/2024",
          "spotsAvailable": 0,
          "lastUpdated": "9/9/2024 3:10:00 AM"
        },
        {
          "date": "10/17/2024_10/20/2024",
          "spotsAvailable": 0,
          "lastUpdated": "9/9/2024 3:10:08 AM"
        },
        {
          "date": "10/24/2024_10/27/2024",
          "spotsAvailable": 0,
          "lastUpdated": "9/9/2024 3:10:16 AM"
        },
        {
          "date": "10/31/2024_11/03/2024",
          "spotsAvailable": 0,
          "lastUpdated": "9/9/2024 3:10:24 AM"
        },
        {
          "date": "11/07/2024_11/10/2024",
          "spotsAvailable": 0,
          "lastUpdated": "9/9/2024 3:10:32 AM"
        },
        {
          "date": "11/14/2024_11/17/2024",
          "spotsAvailable": 0,
          "lastUpdated": "9/9/2024 3:10:39 AM"
        },
        {
          "date": "11/21/2024_11/24/2024",
          "spotsAvailable": 0,
          "lastUpdated": "9/9/2024 3:10:46 AM"
        },
        {
          "date": "11/28/2024_12/01/2024",
          "spotsAvailable": 0,
          "lastUpdated": "9/9/2024 3:10:54 AM"
        },
        {
          "date": "12/05/2024_12/08/2024",
          "spotsAvailable": 0,
          "lastUpdated": "9/9/2024 3:11:01 AM"
        },
        {
          "date": "12/12/2024_12/15/2024",
          "spotsAvailable": 0,
          "lastUpdated": "9/9/2024 3:11:08 AM"
        },
        {
          "date": "12/19/2024_12/22/2024",
          "spotsAvailable": 0,
          "lastUpdated": "9/9/2024 3:11:15 AM"
        },
        {
          "date": "12/26/2024_12/29/2024",
          "spotsAvailable": 0,
          "lastUpdated": "9/9/2024 3:11:23 AM"
        },
        {
          "date": "01/02/2025_01/05/2025",
          "spotsAvailable": 0,
          "lastUpdated": "9/9/2024 3:11:31 AM"
        },
        {
          "date": "01/09/2025_01/12/2025",
          "spotsAvailable": 0,
          "lastUpdated": "9/9/2024 3:11:38 AM"
        },
        {
          "date": "01/16/2025_01/19/2025",
          "spotsAvailable": 0,
          "lastUpdated": "9/9/2024 3:11:45 AM"
        },
        {
          "date": "01/23/2025_01/26/2025",
          "spotsAvailable": 0,
          "lastUpdated": "9/9/2024 3:11:52 AM"
        },
        {
          "date": "01/30/2025_02/02/2025",
          "spotsAvailable": 0,
          "lastUpdated": "9/9/2024 3:11:59 AM"
        },
        {
          "date": "02/06/2025_02/09/2025",
          "spotsAvailable": 0,
          "lastUpdated": "9/9/2024 3:12:06 AM"
        },
        {
          "date": "02/13/2025_02/16/2025",
          "spotsAvailable": 0,
          "lastUpdated": "9/9/2024 3:12:14 AM"
        },
        {
          "date": "02/20/2025_02/23/2025",
          "spotsAvailable": 0,
          "lastUpdated": "9/9/2024 3:12:21 AM"
        },
        {
          "date": "02/27/2025_03/02/2025",
          "spotsAvailable": 0,
          "lastUpdated": "9/9/2024 3:12:29 AM"
        },
        {
          "date": "03/06/2025_03/09/2025",
          "spotsAvailable": 0,
          "lastUpdated": "9/9/2024 3:12:37 AM"
        }
      ]
    },
    {
      "campground": "south_carlsbad_sb",
      "dates": [
        {
          "date": "08/22/2024_08/25/2024",
          "spotsAvailable": 0,
          "lastUpdated": "8/22/2024 11:13:16 PM"
        },
        {
          "date": "08/29/2024_09/01/2024",
          "spotsAvailable": 0,
          "lastUpdated": "8/30/2024 12:19:54 AM"
        },
        {
          "date": "09/05/2024_09/08/2024",
          "spotsAvailable": 0,
          "lastUpdated": "9/5/2024 7:06:19 PM"
        },
        {
          "date": "09/12/2024_09/15/2024",
          "spotsAvailable": 0,
          "lastUpdated": "9/9/2024 3:16:05 AM"
        },
        {
          "date": "09/19/2024_09/22/2024",
          "spotsAvailable": 0,
          "lastUpdated": "9/9/2024 3:16:12 AM"
        },
        {
          "date": "09/26/2024_09/29/2024",
          "spotsAvailable": 0,
          "lastUpdated": "9/9/2024 3:16:19 AM"
        },
        {
          "date": "10/03/2024_10/06/2024",
          "spotsAvailable": 0,
          "lastUpdated": "9/9/2024 3:16:27 AM"
        },
        {
          "date": "10/10/2024_10/13/2024",
          "spotsAvailable": 0,
          "lastUpdated": "9/9/2024 3:16:34 AM"
        },
        {
          "date": "10/17/2024_10/20/2024",
          "spotsAvailable": 0,
          "lastUpdated": "9/9/2024 3:16:43 AM"
        },
        {
          "date": "10/24/2024_10/27/2024",
          "spotsAvailable": 0,
          "lastUpdated": "9/9/2024 3:16:51 AM"
        },
        {
          "date": "10/31/2024_11/03/2024",
          "spotsAvailable": 0,
          "lastUpdated": "9/9/2024 3:16:59 AM"
        },
        {
          "date": "11/07/2024_11/10/2024",
          "spotsAvailable": 0,
          "lastUpdated": "9/9/2024 3:17:07 AM"
        },
        {
          "date": "11/14/2024_11/17/2024",
          "spotsAvailable": 0,
          "lastUpdated": "9/9/2024 3:17:14 AM"
        },
        {
          "date": "11/21/2024_11/24/2024",
          "spotsAvailable": 0,
          "lastUpdated": "9/9/2024 3:17:22 AM"
        },
        {
          "date": "11/28/2024_12/01/2024",
          "spotsAvailable": 0,
          "lastUpdated": "9/9/2024 3:17:29 AM"
        },
        {
          "date": "12/05/2024_12/08/2024",
          "spotsAvailable": 0,
          "lastUpdated": "9/9/2024 3:17:37 AM"
        },
        {
          "date": "12/12/2024_12/15/2024",
          "spotsAvailable": 0,
          "lastUpdated": "9/9/2024 3:17:45 AM"
        },
        {
          "date": "12/19/2024_12/22/2024",
          "spotsAvailable": 0,
          "lastUpdated": "9/9/2024 3:17:52 AM"
        },
        {
          "date": "12/26/2024_12/29/2024",
          "spotsAvailable": 0,
          "lastUpdated": "9/9/2024 3:17:59 AM"
        },
        {
          "date": "01/02/2025_01/05/2025",
          "spotsAvailable": 0,
          "lastUpdated": "9/9/2024 3:18:06 AM"
        },
        {
          "date": "01/09/2025_01/12/2025",
          "spotsAvailable": 0,
          "lastUpdated": "9/9/2024 3:18:13 AM"
        },
        {
          "date": "01/16/2025_01/19/2025",
          "spotsAvailable": 0,
          "lastUpdated": "9/9/2024 3:18:20 AM"
        },
        {
          "date": "01/23/2025_01/26/2025",
          "spotsAvailable": 0,
          "lastUpdated": "9/9/2024 3:18:27 AM"
        },
        {
          "date": "01/30/2025_02/02/2025",
          "spotsAvailable": 0,
          "lastUpdated": "9/9/2024 3:18:34 AM"
        },
        {
          "date": "02/06/2025_02/09/2025",
          "spotsAvailable": 0,
          "lastUpdated": "9/9/2024 3:18:42 AM"
        },
        {
          "date": "02/13/2025_02/16/2025",
          "spotsAvailable": 0,
          "lastUpdated": "9/9/2024 3:18:49 AM"
        },
        {
          "date": "02/20/2025_02/23/2025",
          "spotsAvailable": 0,
          "lastUpdated": "9/9/2024 3:18:56 AM"
        },
        {
          "date": "02/27/2025_03/02/2025",
          "spotsAvailable": 0,
          "lastUpdated": "9/9/2024 3:19:03 AM"
        },
        {
          "date": "03/06/2025_03/09/2025",
          "spotsAvailable": 0,
          "lastUpdated": "9/9/2024 3:19:11 AM"
        }
      ]
    },
    {
      "campground": "carpinteria",
      "dates": [
        {
          "date": "08/22/2024_08/25/2024",
          "spotsAvailable": 0,
          "lastUpdated": "8/23/2024 12:06:24 AM"
        },
        {
          "date": "08/29/2024_09/01/2024",
          "spotsAvailable": 0,
          "lastUpdated": "8/30/2024 12:13:20 AM"
        },
        {
          "date": "09/05/2024_09/08/2024",
          "spotsAvailable": 0,
          "lastUpdated": "9/5/2024 3:02:51 PM"
        },
        {
          "date": "09/12/2024_09/15/2024",
          "spotsAvailable": 0,
          "lastUpdated": "9/9/2024 3:19:55 AM"
        },
        {
          "date": "09/19/2024_09/22/2024",
          "spotsAvailable": 0,
          "lastUpdated": "9/9/2024 3:20:04 AM"
        },
        {
          "date": "09/26/2024_09/29/2024",
          "spotsAvailable": 0,
          "lastUpdated": "9/9/2024 3:20:11 AM"
        },
        {
          "date": "10/03/2024_10/06/2024",
          "spotsAvailable": 0,
          "lastUpdated": "9/9/2024 3:20:19 AM"
        },
        {
          "date": "10/10/2024_10/13/2024",
          "spotsAvailable": 0,
          "lastUpdated": "9/9/2024 3:20:27 AM"
        },
        {
          "date": "10/17/2024_10/20/2024",
          "spotsAvailable": 0,
          "lastUpdated": "9/9/2024 3:20:35 AM"
        },
        {
          "date": "10/24/2024_10/27/2024",
          "spotsAvailable": 0,
          "lastUpdated": "9/9/2024 3:20:43 AM"
        },
        {
          "date": "10/31/2024_11/03/2024",
          "spotsAvailable": 0,
          "lastUpdated": "9/9/2024 3:20:51 AM"
        },
        {
          "date": "11/07/2024_11/10/2024",
          "spotsAvailable": 0,
          "lastUpdated": "9/9/2024 3:20:58 AM"
        },
        {
          "date": "11/14/2024_11/17/2024",
          "spotsAvailable": 0,
          "lastUpdated": "9/9/2024 3:21:06 AM"
        },
        {
          "date": "11/21/2024_11/24/2024",
          "spotsAvailable": 0,
          "lastUpdated": "9/9/2024 3:21:14 AM"
        },
        {
          "date": "11/28/2024_12/01/2024",
          "spotsAvailable": 0,
          "lastUpdated": "9/9/2024 3:21:21 AM"
        },
        {
          "date": "12/05/2024_12/08/2024",
          "spotsAvailable": 0,
          "lastUpdated": "9/9/2024 3:21:28 AM"
        },
        {
          "date": "12/12/2024_12/15/2024",
          "spotsAvailable": 0,
          "lastUpdated": "9/9/2024 3:21:36 AM"
        },
        {
          "date": "12/19/2024_12/22/2024",
          "spotsAvailable": 0,
          "lastUpdated": "9/9/2024 3:21:43 AM"
        },
        {
          "date": "12/26/2024_12/29/2024",
          "spotsAvailable": 0,
          "lastUpdated": "9/9/2024 3:21:51 AM"
        },
        {
          "date": "01/02/2025_01/05/2025",
          "spotsAvailable": 0,
          "lastUpdated": "9/9/2024 3:21:57 AM"
        },
        {
          "date": "01/09/2025_01/12/2025",
          "spotsAvailable": 0,
          "lastUpdated": "9/9/2024 3:22:05 AM"
        },
        {
          "date": "01/16/2025_01/19/2025",
          "spotsAvailable": 0,
          "lastUpdated": "9/9/2024 3:22:12 AM"
        },
        {
          "date": "01/23/2025_01/26/2025",
          "spotsAvailable": 0,
          "lastUpdated": "9/9/2024 3:22:19 AM"
        },
        {
          "date": "01/30/2025_02/02/2025",
          "spotsAvailable": 0,
          "lastUpdated": "9/9/2024 3:22:27 AM"
        },
        {
          "date": "02/06/2025_02/09/2025",
          "spotsAvailable": 0,
          "lastUpdated": "9/9/2024 3:22:35 AM"
        },
        {
          "date": "02/13/2025_02/16/2025",
          "spotsAvailable": 0,
          "lastUpdated": "9/9/2024 3:22:42 AM"
        },
        {
          "date": "02/20/2025_02/23/2025",
          "spotsAvailable": 0,
          "lastUpdated": "9/9/2024 3:22:50 AM"
        },
        {
          "date": "02/27/2025_03/02/2025",
          "spotsAvailable": 0,
          "lastUpdated": "9/9/2024 3:22:57 AM"
        },
        {
          "date": "03/06/2025_03/09/2025",
          "spotsAvailable": 0,
          "lastUpdated": "9/9/2024 3:23:05 AM"
        }
      ]
    },
    {
      "campground": "leo_carillo",
      "dates": [
        {
          "date": "08/22/2024_08/25/2024",
          "spotsAvailable": 0,
          "lastUpdated": "8/22/2024 11:59:20 PM"
        },
        {
          "date": "08/29/2024_09/01/2024",
          "spotsAvailable": 0,
          "lastUpdated": "8/30/2024 12:02:56 AM"
        },
        {
          "date": "09/05/2024_09/08/2024",
          "spotsAvailable": 0,
          "lastUpdated": "9/5/2024 3:23:09 PM"
        },
        {
          "date": "09/12/2024_09/15/2024",
          "spotsAvailable": 0,
          "lastUpdated": "9/9/2024 2:59:22 AM"
        },
        {
          "date": "09/19/2024_09/22/2024",
          "spotsAvailable": 0,
          "lastUpdated": "9/9/2024 2:59:30 AM"
        },
        {
          "date": "09/26/2024_09/29/2024",
          "spotsAvailable": 0,
          "lastUpdated": "9/9/2024 2:59:37 AM"
        },
        {
          "date": "10/03/2024_10/06/2024",
          "spotsAvailable": 0,
          "lastUpdated": "9/9/2024 2:59:45 AM"
        },
        {
          "date": "10/10/2024_10/13/2024",
          "spotsAvailable": 0,
          "lastUpdated": "9/9/2024 2:59:53 AM"
        },
        {
          "date": "10/17/2024_10/20/2024",
          "spotsAvailable": 0,
          "lastUpdated": "9/9/2024 3:00:00 AM"
        },
        {
          "date": "10/24/2024_10/27/2024",
          "spotsAvailable": 0,
          "lastUpdated": "9/9/2024 3:00:09 AM"
        },
        {
          "date": "10/31/2024_11/03/2024",
          "spotsAvailable": 0,
          "lastUpdated": "9/9/2024 3:00:17 AM"
        },
        {
          "date": "11/07/2024_11/10/2024",
          "spotsAvailable": 0,
          "lastUpdated": "9/9/2024 3:00:26 AM"
        },
        {
          "date": "11/14/2024_11/17/2024",
          "spotsAvailable": 0,
          "lastUpdated": "9/9/2024 3:00:33 AM"
        },
        {
          "date": "11/21/2024_11/24/2024",
          "spotsAvailable": 0,
          "lastUpdated": "9/9/2024 3:00:40 AM"
        },
        {
          "date": "11/28/2024_12/01/2024",
          "spotsAvailable": 0,
          "lastUpdated": "9/9/2024 3:00:47 AM"
        },
        {
          "date": "12/05/2024_12/08/2024",
          "spotsAvailable": 28,
          "lastUpdated": "9/9/2024 3:00:55 AM"
        },
        {
          "date": "12/12/2024_12/15/2024",
          "spotsAvailable": 65,
          "lastUpdated": "9/9/2024 3:01:02 AM"
        },
        {
          "date": "12/19/2024_12/22/2024",
          "spotsAvailable": 103,
          "lastUpdated": "9/9/2024 3:01:09 AM"
        },
        {
          "date": "12/26/2024_12/29/2024",
          "spotsAvailable": 61,
          "lastUpdated": "9/9/2024 3:01:17 AM"
        },
        {
          "date": "01/02/2025_01/05/2025",
          "spotsAvailable": 76,
          "lastUpdated": "9/9/2024 3:01:24 AM"
        },
        {
          "date": "01/09/2025_01/12/2025",
          "spotsAvailable": 102,
          "lastUpdated": "9/9/2024 3:01:33 AM"
        },
        {
          "date": "01/16/2025_01/19/2025",
          "spotsAvailable": 54,
          "lastUpdated": "9/9/2024 3:01:41 AM"
        },
        {
          "date": "01/23/2025_01/26/2025",
          "spotsAvailable": 101,
          "lastUpdated": "9/9/2024 3:01:49 AM"
        },
        {
          "date": "01/30/2025_02/02/2025",
          "spotsAvailable": 106,
          "lastUpdated": "9/9/2024 3:01:56 AM"
        },
        {
          "date": "02/06/2025_02/09/2025",
          "spotsAvailable": 86,
          "lastUpdated": "9/9/2024 3:02:04 AM"
        },
        {
          "date": "02/13/2025_02/16/2025",
          "spotsAvailable": 38,
          "lastUpdated": "9/9/2024 3:02:12 AM"
        },
        {
          "date": "02/20/2025_02/23/2025",
          "spotsAvailable": 100,
          "lastUpdated": "9/9/2024 3:02:19 AM"
        },
        {
          "date": "02/27/2025_03/02/2025",
          "spotsAvailable": 89,
          "lastUpdated": "9/9/2024 3:02:27 AM"
        },
        {
          "date": "03/06/2025_03/09/2025",
          "spotsAvailable": 102,
          "lastUpdated": "9/9/2024 3:02:35 AM"
        }
      ]
    },
    {
      "campground": "morro_bay",
      "dates": [
        {
          "date": "08/22/2024_08/25/2024",
          "spotsAvailable": 0,
          "lastUpdated": "8/23/2024 12:17:04 AM"
        },
        {
          "date": "08/29/2024_09/01/2024",
          "spotsAvailable": 0,
          "lastUpdated": "8/30/2024 12:16:38 AM"
        },
        {
          "date": "09/05/2024_09/08/2024",
          "spotsAvailable": 0,
          "lastUpdated": "9/5/2024 3:16:31 PM"
        },
        {
          "date": "09/12/2024_09/15/2024",
          "spotsAvailable": 0,
          "lastUpdated": "9/9/2024 3:06:06 AM"
        },
        {
          "date": "09/19/2024_09/22/2024",
          "spotsAvailable": 0,
          "lastUpdated": "9/9/2024 3:06:14 AM"
        },
        {
          "date": "09/26/2024_09/29/2024",
          "spotsAvailable": 0,
          "lastUpdated": "9/9/2024 3:06:22 AM"
        },
        {
          "date": "10/03/2024_10/06/2024",
          "spotsAvailable": 0,
          "lastUpdated": "9/9/2024 3:06:29 AM"
        },
        {
          "date": "10/10/2024_10/13/2024",
          "spotsAvailable": 0,
          "lastUpdated": "9/9/2024 3:06:37 AM"
        },
        {
          "date": "10/17/2024_10/20/2024",
          "spotsAvailable": 0,
          "lastUpdated": "9/9/2024 3:06:45 AM"
        },
        {
          "date": "10/24/2024_10/27/2024",
          "spotsAvailable": 0,
          "lastUpdated": "9/9/2024 3:06:53 AM"
        },
        {
          "date": "10/31/2024_11/03/2024",
          "spotsAvailable": 0,
          "lastUpdated": "9/9/2024 3:07:02 AM"
        },
        {
          "date": "11/07/2024_11/10/2024",
          "spotsAvailable": 0,
          "lastUpdated": "9/9/2024 3:07:10 AM"
        },
        {
          "date": "11/14/2024_11/17/2024",
          "spotsAvailable": 9,
          "lastUpdated": "9/9/2024 3:07:17 AM"
        },
        {
          "date": "11/21/2024_11/24/2024",
          "spotsAvailable": 1,
          "lastUpdated": "9/9/2024 3:07:25 AM"
        },
        {
          "date": "11/28/2024_12/01/2024",
          "spotsAvailable": 0,
          "lastUpdated": "9/9/2024 3:07:34 AM"
        },
        {
          "date": "12/05/2024_12/08/2024",
          "spotsAvailable": 0,
          "lastUpdated": "9/9/2024 3:07:42 AM"
        },
        {
          "date": "12/12/2024_12/15/2024",
          "spotsAvailable": 0,
          "lastUpdated": "9/9/2024 3:07:50 AM"
        },
        {
          "date": "12/19/2024_12/22/2024",
          "spotsAvailable": 0,
          "lastUpdated": "9/9/2024 3:07:57 AM"
        },
        {
          "date": "12/26/2024_12/29/2024",
          "spotsAvailable": 0,
          "lastUpdated": "9/9/2024 3:08:04 AM"
        },
        {
          "date": "01/02/2025_01/05/2025",
          "spotsAvailable": 0,
          "lastUpdated": "9/9/2024 3:08:12 AM"
        },
        {
          "date": "01/09/2025_01/12/2025",
          "spotsAvailable": 0,
          "lastUpdated": "9/9/2024 3:08:20 AM"
        },
        {
          "date": "01/16/2025_01/19/2025",
          "spotsAvailable": 0,
          "lastUpdated": "9/9/2024 3:08:27 AM"
        },
        {
          "date": "01/23/2025_01/26/2025",
          "spotsAvailable": 0,
          "lastUpdated": "9/9/2024 3:08:34 AM"
        },
        {
          "date": "01/30/2025_02/02/2025",
          "spotsAvailable": 0,
          "lastUpdated": "9/9/2024 3:08:42 AM"
        },
        {
          "date": "02/06/2025_02/09/2025",
          "spotsAvailable": 0,
          "lastUpdated": "9/9/2024 3:08:49 AM"
        },
        {
          "date": "02/13/2025_02/16/2025",
          "spotsAvailable": 0,
          "lastUpdated": "9/9/2024 3:08:56 AM"
        },
        {
          "date": "02/20/2025_02/23/2025",
          "spotsAvailable": 0,
          "lastUpdated": "9/9/2024 3:09:04 AM"
        },
        {
          "date": "02/27/2025_03/02/2025",
          "spotsAvailable": 0,
          "lastUpdated": "9/9/2024 3:09:11 AM"
        },
        {
          "date": "03/06/2025_03/09/2025",
          "spotsAvailable": 0,
          "lastUpdated": "9/9/2024 3:09:19 AM"
        }
      ]
    },
    {
      "campground": "emma_wood",
      "dates": [
        {
          "date": "08/22/2024_08/25/2024",
          "spotsAvailable": 0,
          "lastUpdated": "8/23/2024 12:13:11 AM"
        },
        {
          "date": "08/29/2024_09/01/2024",
          "spotsAvailable": 0,
          "lastUpdated": "8/29/2024 11:10:47 PM"
        },
        {
          "date": "09/05/2024_09/08/2024",
          "spotsAvailable": 0,
          "lastUpdated": "9/5/2024 6:59:18 PM"
        },
        {
          "date": "09/12/2024_09/15/2024",
          "spotsAvailable": 1,
          "lastUpdated": "9/9/2024 3:12:48 AM"
        },
        {
          "date": "09/19/2024_09/22/2024",
          "spotsAvailable": 1,
          "lastUpdated": "9/9/2024 3:12:55 AM"
        },
        {
          "date": "09/26/2024_09/29/2024",
          "spotsAvailable": 0,
          "lastUpdated": "9/9/2024 3:13:03 AM"
        },
        {
          "date": "10/03/2024_10/06/2024",
          "spotsAvailable": 1,
          "lastUpdated": "9/9/2024 3:13:10 AM"
        },
        {
          "date": "10/10/2024_10/13/2024",
          "spotsAvailable": 1,
          "lastUpdated": "9/9/2024 3:13:17 AM"
        },
        {
          "date": "10/17/2024_10/20/2024",
          "spotsAvailable": 0,
          "lastUpdated": "9/9/2024 3:13:25 AM"
        },
        {
          "date": "10/24/2024_10/27/2024",
          "spotsAvailable": 3,
          "lastUpdated": "9/9/2024 3:13:33 AM"
        },
        {
          "date": "10/31/2024_11/03/2024",
          "spotsAvailable": 3,
          "lastUpdated": "9/9/2024 3:13:40 AM"
        },
        {
          "date": "11/07/2024_11/10/2024",
          "spotsAvailable": 3,
          "lastUpdated": "9/9/2024 3:13:48 AM"
        },
        {
          "date": "11/14/2024_11/17/2024",
          "spotsAvailable": 3,
          "lastUpdated": "9/9/2024 3:13:56 AM"
        },
        {
          "date": "11/21/2024_11/24/2024",
          "spotsAvailable": 3,
          "lastUpdated": "9/9/2024 3:14:04 AM"
        },
        {
          "date": "11/28/2024_12/01/2024",
          "spotsAvailable": 3,
          "lastUpdated": "9/9/2024 3:14:11 AM"
        },
        {
          "date": "12/05/2024_12/08/2024",
          "spotsAvailable": 3,
          "lastUpdated": "9/9/2024 3:14:18 AM"
        },
        {
          "date": "12/12/2024_12/15/2024",
          "spotsAvailable": 3,
          "lastUpdated": "9/9/2024 3:14:26 AM"
        },
        {
          "date": "12/19/2024_12/22/2024",
          "spotsAvailable": 3,
          "lastUpdated": "9/9/2024 3:14:33 AM"
        },
        {
          "date": "12/26/2024_12/29/2024",
          "spotsAvailable": 3,
          "lastUpdated": "9/9/2024 3:14:40 AM"
        },
        {
          "date": "01/02/2025_01/05/2025",
          "spotsAvailable": 3,
          "lastUpdated": "9/9/2024 3:14:47 AM"
        },
        {
          "date": "01/09/2025_01/12/2025",
          "spotsAvailable": 3,
          "lastUpdated": "9/9/2024 3:14:54 AM"
        },
        {
          "date": "01/16/2025_01/19/2025",
          "spotsAvailable": 3,
          "lastUpdated": "9/9/2024 3:15:02 AM"
        },
        {
          "date": "01/23/2025_01/26/2025",
          "spotsAvailable": 3,
          "lastUpdated": "9/9/2024 3:15:10 AM"
        },
        {
          "date": "01/30/2025_02/02/2025",
          "spotsAvailable": 3,
          "lastUpdated": "9/9/2024 3:15:17 AM"
        },
        {
          "date": "02/06/2025_02/09/2025",
          "spotsAvailable": 3,
          "lastUpdated": "9/9/2024 3:15:24 AM"
        },
        {
          "date": "02/13/2025_02/16/2025",
          "spotsAvailable": 3,
          "lastUpdated": "9/9/2024 3:15:32 AM"
        },
        {
          "date": "02/20/2025_02/23/2025",
          "spotsAvailable": 3,
          "lastUpdated": "9/9/2024 3:15:39 AM"
        },
        {
          "date": "02/27/2025_03/02/2025",
          "spotsAvailable": 3,
          "lastUpdated": "9/9/2024 3:15:46 AM"
        },
        {
          "date": "03/06/2025_03/09/2025",
          "spotsAvailable": 3,
          "lastUpdated": "9/9/2024 3:15:53 AM"
        }
      ]
    },
    {
      "campground": "pfeiffer",
      "dates": [
        {
          "date": "08/22/2024_08/25/2024",
          "spotsAvailable": 0,
          "lastUpdated": "8/22/2024 10:59:20 PM"
        },
        {
          "date": "08/29/2024_09/01/2024",
          "spotsAvailable": 0,
          "lastUpdated": "8/30/2024 12:09:58 AM"
        },
        {
          "date": "09/05/2024_09/08/2024",
          "spotsAvailable": 0,
          "lastUpdated": "9/5/2024 3:19:48 PM"
        },
        {
          "date": "09/12/2024_09/15/2024",
          "spotsAvailable": 0,
          "lastUpdated": "9/9/2024 2:10:10 AM"
        },
        {
          "date": "09/19/2024_09/22/2024",
          "spotsAvailable": 0,
          "lastUpdated": "9/9/2024 2:10:19 AM"
        },
        {
          "date": "09/26/2024_09/29/2024",
          "spotsAvailable": 0,
          "lastUpdated": "9/9/2024 2:10:26 AM"
        },
        {
          "date": "10/03/2024_10/06/2024",
          "spotsAvailable": 0,
          "lastUpdated": "9/9/2024 2:10:34 AM"
        },
        {
          "date": "10/10/2024_10/13/2024",
          "spotsAvailable": 0,
          "lastUpdated": "9/9/2024 2:10:41 AM"
        },
        {
          "date": "10/17/2024_10/20/2024",
          "spotsAvailable": 0,
          "lastUpdated": "9/9/2024 2:10:50 AM"
        },
        {
          "date": "10/24/2024_10/27/2024",
          "spotsAvailable": 0,
          "lastUpdated": "9/9/2024 2:10:57 AM"
        },
        {
          "date": "10/31/2024_11/03/2024",
          "spotsAvailable": 0,
          "lastUpdated": "9/9/2024 2:11:06 AM"
        },
        {
          "date": "11/07/2024_11/10/2024",
          "spotsAvailable": 0,
          "lastUpdated": "9/9/2024 2:11:13 AM"
        },
        {
          "date": "11/14/2024_11/17/2024",
          "spotsAvailable": 0,
          "lastUpdated": "9/9/2024 2:11:20 AM"
        },
        {
          "date": "11/21/2024_11/24/2024",
          "spotsAvailable": 0,
          "lastUpdated": "9/9/2024 2:11:28 AM"
        },
        {
          "date": "11/28/2024_12/01/2024",
          "spotsAvailable": 0,
          "lastUpdated": "9/9/2024 2:11:35 AM"
        },
        {
          "date": "12/05/2024_12/08/2024",
          "spotsAvailable": 0,
          "lastUpdated": "9/9/2024 2:11:42 AM"
        },
        {
          "date": "12/12/2024_12/15/2024",
          "spotsAvailable": 0,
          "lastUpdated": "9/9/2024 2:11:50 AM"
        },
        {
          "date": "12/19/2024_12/22/2024",
          "spotsAvailable": 0,
          "lastUpdated": "9/9/2024 2:11:58 AM"
        },
        {
          "date": "12/26/2024_12/29/2024",
          "spotsAvailable": 0,
          "lastUpdated": "9/9/2024 2:12:05 AM"
        },
        {
          "date": "01/02/2025_01/05/2025",
          "spotsAvailable": 0,
          "lastUpdated": "9/9/2024 2:12:12 AM"
        },
        {
          "date": "01/09/2025_01/12/2025",
          "spotsAvailable": 0,
          "lastUpdated": "9/9/2024 2:12:19 AM"
        },
        {
          "date": "01/16/2025_01/19/2025",
          "spotsAvailable": 0,
          "lastUpdated": "9/9/2024 2:12:26 AM"
        },
        {
          "date": "01/23/2025_01/26/2025",
          "spotsAvailable": 0,
          "lastUpdated": "9/9/2024 2:12:33 AM"
        },
        {
          "date": "01/30/2025_02/02/2025",
          "spotsAvailable": 0,
          "lastUpdated": "9/9/2024 2:12:40 AM"
        },
        {
          "date": "02/06/2025_02/09/2025",
          "spotsAvailable": 0,
          "lastUpdated": "9/9/2024 2:12:48 AM"
        },
        {
          "date": "02/13/2025_02/16/2025",
          "spotsAvailable": 0,
          "lastUpdated": "9/9/2024 2:12:55 AM"
        },
        {
          "date": "02/20/2025_02/23/2025",
          "spotsAvailable": 0,
          "lastUpdated": "9/9/2024 2:13:02 AM"
        },
        {
          "date": "02/27/2025_03/02/2025",
          "spotsAvailable": 0,
          "lastUpdated": "9/9/2024 2:13:09 AM"
        },
        {
          "date": "03/06/2025_03/09/2025",
          "spotsAvailable": 0,
          "lastUpdated": "9/9/2024 2:13:17 AM"
        }
      ]
    },
    {
      "campground": "henry_cowell",
      "dates": [
        {
          "date": "08/22/2024_08/25/2024",
          "spotsAvailable": 0,
          "lastUpdated": "8/23/2024 12:09:48 AM"
        },
        {
          "date": "08/29/2024_09/01/2024",
          "spotsAvailable": 0,
          "lastUpdated": "8/29/2024 11:59:20 PM"
        },
        {
          "date": "09/05/2024_09/08/2024",
          "spotsAvailable": 0,
          "lastUpdated": "9/5/2024 7:10:14 PM"
        },
        {
          "date": "09/12/2024_09/15/2024",
          "spotsAvailable": 0,
          "lastUpdated": "9/9/2024 3:02:46 AM"
        },
        {
          "date": "09/19/2024_09/22/2024",
          "spotsAvailable": 0,
          "lastUpdated": "9/9/2024 3:02:54 AM"
        },
        {
          "date": "09/26/2024_09/29/2024",
          "spotsAvailable": 0,
          "lastUpdated": "9/9/2024 3:03:03 AM"
        },
        {
          "date": "10/03/2024_10/06/2024",
          "spotsAvailable": 0,
          "lastUpdated": "9/9/2024 3:03:11 AM"
        },
        {
          "date": "10/10/2024_10/13/2024",
          "spotsAvailable": 0,
          "lastUpdated": "9/9/2024 3:03:18 AM"
        },
        {
          "date": "10/17/2024_10/20/2024",
          "spotsAvailable": 0,
          "lastUpdated": "9/9/2024 3:03:26 AM"
        },
        {
          "date": "10/24/2024_10/27/2024",
          "spotsAvailable": 0,
          "lastUpdated": "9/9/2024 3:03:33 AM"
        },
        {
          "date": "10/31/2024_11/03/2024",
          "spotsAvailable": 0,
          "lastUpdated": "9/9/2024 3:03:41 AM"
        },
        {
          "date": "11/07/2024_11/10/2024",
          "spotsAvailable": 0,
          "lastUpdated": "9/9/2024 3:03:48 AM"
        },
        {
          "date": "11/14/2024_11/17/2024",
          "spotsAvailable": 0,
          "lastUpdated": "9/9/2024 3:03:56 AM"
        },
        {
          "date": "11/21/2024_11/24/2024",
          "spotsAvailable": 0,
          "lastUpdated": "9/9/2024 3:04:04 AM"
        },
        {
          "date": "11/28/2024_12/01/2024",
          "spotsAvailable": 0,
          "lastUpdated": "9/9/2024 3:04:11 AM"
        },
        {
          "date": "12/05/2024_12/08/2024",
          "spotsAvailable": 0,
          "lastUpdated": "9/9/2024 3:04:19 AM"
        },
        {
          "date": "12/12/2024_12/15/2024",
          "spotsAvailable": 0,
          "lastUpdated": "9/9/2024 3:04:26 AM"
        },
        {
          "date": "12/19/2024_12/22/2024",
          "spotsAvailable": 0,
          "lastUpdated": "9/9/2024 3:04:34 AM"
        },
        {
          "date": "12/26/2024_12/29/2024",
          "spotsAvailable": 0,
          "lastUpdated": "9/9/2024 3:04:41 AM"
        },
        {
          "date": "01/02/2025_01/05/2025",
          "spotsAvailable": 0,
          "lastUpdated": "9/9/2024 3:04:49 AM"
        },
        {
          "date": "01/09/2025_01/12/2025",
          "spotsAvailable": 0,
          "lastUpdated": "9/9/2024 3:04:56 AM"
        },
        {
          "date": "01/16/2025_01/19/2025",
          "spotsAvailable": 0,
          "lastUpdated": "9/9/2024 3:05:04 AM"
        },
        {
          "date": "01/23/2025_01/26/2025",
          "spotsAvailable": 0,
          "lastUpdated": "9/9/2024 3:05:12 AM"
        },
        {
          "date": "01/30/2025_02/02/2025",
          "spotsAvailable": 0,
          "lastUpdated": "9/9/2024 3:05:19 AM"
        },
        {
          "date": "02/06/2025_02/09/2025",
          "spotsAvailable": 0,
          "lastUpdated": "9/9/2024 3:05:26 AM"
        },
        {
          "date": "02/13/2025_02/16/2025",
          "spotsAvailable": 0,
          "lastUpdated": "9/9/2024 3:05:33 AM"
        },
        {
          "date": "02/20/2025_02/23/2025",
          "spotsAvailable": 0,
          "lastUpdated": "9/9/2024 3:05:40 AM"
        },
        {
          "date": "02/27/2025_03/02/2025",
          "spotsAvailable": 0,
          "lastUpdated": "9/9/2024 3:05:47 AM"
        },
        {
          "date": "03/06/2025_03/09/2025",
          "spotsAvailable": 0,
          "lastUpdated": "9/9/2024 3:05:54 AM"
        }
      ]
    }
  ]
}