{
  "campground_dates": [
    {
      "campground": "pfeiffer",
      "dates": [
        {
          "date": "04/28/2023_04/30/2023",
          "spotsAvailable": 0,
          "lastUpdated": "4/26/2023 2:24:02 PM"
        },
        {
          "date": "05/05/2023_05/07/2023",
          "spotsAvailable": 0,
          "lastUpdated": "5/4/2023 11:00:33 PM"
        },
        {
          "date": "05/12/2023_05/14/2023",
          "spotsAvailable": 0,
          "lastUpdated": "5/12/2023 12:00:37 AM"
        },
        {
          "date": "05/19/2023_05/21/2023",
          "spotsAvailable": 0,
          "lastUpdated": "5/18/2023 2:00:33 AM"
        },
        {
          "date": "05/26/2023_05/28/2023",
          "spotsAvailable": 0,
          "lastUpdated": "5/26/2023 12:00:34 AM"
        },
        {
          "date": "06/02/2023_06/04/2023",
          "spotsAvailable": 0,
          "lastUpdated": "6/2/2023 12:00:36 AM"
        },
        {
          "date": "06/09/2023_06/11/2023",
          "spotsAvailable": 0,
          "lastUpdated": "6/3/2023 7:00:31 AM"
        },
        {
          "date": "06/16/2023_06/18/2023",
          "spotsAvailable": 0,
          "lastUpdated": "6/3/2023 7:00:38 AM"
        },
        {
          "date": "06/23/2023_06/25/2023",
          "spotsAvailable": 0,
          "lastUpdated": "6/3/2023 7:00:45 AM"
        },
        {
          "date": "06/30/2023_07/02/2023",
          "spotsAvailable": 0,
          "lastUpdated": "6/3/2023 7:00:54 AM"
        },
        {
          "date": "07/07/2023_07/09/2023",
          "spotsAvailable": 0,
          "lastUpdated": "6/3/2023 7:01:03 AM"
        },
        {
          "date": "07/14/2023_07/16/2023",
          "spotsAvailable": 0,
          "lastUpdated": "6/3/2023 7:01:11 AM"
        },
        {
          "date": "07/21/2023_07/23/2023",
          "spotsAvailable": 0,
          "lastUpdated": "6/3/2023 7:01:19 AM"
        },
        {
          "date": "07/28/2023_07/30/2023",
          "spotsAvailable": 0,
          "lastUpdated": "6/3/2023 7:01:28 AM"
        },
        {
          "date": "08/04/2023_08/06/2023",
          "spotsAvailable": 0,
          "lastUpdated": "6/3/2023 7:01:36 AM"
        },
        {
          "date": "08/11/2023_08/13/2023",
          "spotsAvailable": 0,
          "lastUpdated": "6/3/2023 7:01:43 AM"
        },
        {
          "date": "08/18/2023_08/20/2023",
          "spotsAvailable": 0,
          "lastUpdated": "6/3/2023 7:01:51 AM"
        },
        {
          "date": "08/25/2023_08/27/2023",
          "spotsAvailable": 0,
          "lastUpdated": "6/3/2023 7:01:58 AM"
        },
        {
          "date": "09/01/2023_09/03/2023",
          "spotsAvailable": 0,
          "lastUpdated": "6/3/2023 7:02:05 AM"
        },
        {
          "date": "09/08/2023_09/10/2023",
          "spotsAvailable": 0,
          "lastUpdated": "6/3/2023 7:02:13 AM"
        },
        {
          "date": "09/15/2023_09/17/2023",
          "spotsAvailable": 0,
          "lastUpdated": "6/3/2023 7:02:20 AM"
        },
        {
          "date": "09/22/2023_09/24/2023",
          "spotsAvailable": 0,
          "lastUpdated": "6/3/2023 7:02:27 AM"
        },
        {
          "date": "09/29/2023_10/01/2023",
          "spotsAvailable": 0,
          "lastUpdated": "6/3/2023 7:02:37 AM"
        },
        {
          "date": "10/06/2023_10/08/2023",
          "spotsAvailable": 0,
          "lastUpdated": "6/3/2023 7:02:44 AM"
        },
        {
          "date": "10/13/2023_10/15/2023",
          "spotsAvailable": 0,
          "lastUpdated": "6/3/2023 7:02:52 AM"
        },
        {
          "date": "10/20/2023_10/22/2023",
          "spotsAvailable": 0,
          "lastUpdated": "6/3/2023 7:02:59 AM"
        },
        {
          "date": "10/27/2023_10/29/2023",
          "spotsAvailable": 0,
          "lastUpdated": "6/3/2023 7:03:06 AM"
        },
        {
          "date": "11/03/2023_11/05/2023",
          "spotsAvailable": 35,
          "lastUpdated": "6/3/2023 7:03:14 AM"
        },
        {
          "date": "11/10/2023_11/12/2023",
          "spotsAvailable": 42,
          "lastUpdated": "6/3/2023 7:03:22 AM"
        },
        {
          "date": "11/17/2023_11/19/2023",
          "spotsAvailable": 65,
          "lastUpdated": "6/3/2023 7:03:29 AM"
        },
        {
          "date": "11/24/2023_11/26/2023",
          "spotsAvailable": 62,
          "lastUpdated": "6/3/2023 7:03:38 AM"
        },
        {
          "date": "12/01/2023_12/03/2023",
          "spotsAvailable": 40,
          "lastUpdated": "6/3/2023 7:03:45 AM"
        }
      ]
    },
    {
      "campground": "carpinteria",
      "dates": [
        {
          "date": "04/28/2023_04/30/2023",
          "spotsAvailable": 0,
          "lastUpdated": "4/26/2023 2:25:26 PM"
        },
        {
          "date": "05/05/2023_05/07/2023",
          "spotsAvailable": 2,
          "lastUpdated": "5/4/2023 11:04:01 PM"
        },
        {
          "date": "05/12/2023_05/14/2023",
          "spotsAvailable": 0,
          "lastUpdated": "5/12/2023 12:04:02 AM"
        },
        {
          "date": "05/19/2023_05/21/2023",
          "spotsAvailable": 0,
          "lastUpdated": "5/18/2023 1:04:05 AM"
        },
        {
          "date": "05/26/2023_05/28/2023",
          "spotsAvailable": 0,
          "lastUpdated": "5/26/2023 12:04:07 AM"
        },
        {
          "date": "06/02/2023_06/04/2023",
          "spotsAvailable": 0,
          "lastUpdated": "6/2/2023 12:02:14 AM"
        },
        {
          "date": "06/09/2023_06/11/2023",
          "spotsAvailable": 0,
          "lastUpdated": "6/3/2023 6:04:03 AM"
        },
        {
          "date": "06/16/2023_06/18/2023",
          "spotsAvailable": 0,
          "lastUpdated": "6/3/2023 6:04:11 AM"
        },
        {
          "date": "06/23/2023_06/25/2023",
          "spotsAvailable": 0,
          "lastUpdated": "6/3/2023 6:04:18 AM"
        },
        {
          "date": "06/30/2023_07/02/2023",
          "spotsAvailable": 0,
          "lastUpdated": "6/3/2023 6:04:26 AM"
        },
        {
          "date": "07/07/2023_07/09/2023",
          "spotsAvailable": 0,
          "lastUpdated": "6/3/2023 6:04:33 AM"
        },
        {
          "date": "07/14/2023_07/16/2023",
          "spotsAvailable": 0,
          "lastUpdated": "6/3/2023 6:04:41 AM"
        },
        {
          "date": "07/21/2023_07/23/2023",
          "spotsAvailable": 0,
          "lastUpdated": "6/3/2023 6:04:48 AM"
        },
        {
          "date": "07/28/2023_07/30/2023",
          "spotsAvailable": 0,
          "lastUpdated": "6/3/2023 6:04:56 AM"
        },
        {
          "date": "08/04/2023_08/06/2023",
          "spotsAvailable": 0,
          "lastUpdated": "6/3/2023 6:05:03 AM"
        },
        {
          "date": "08/11/2023_08/13/2023",
          "spotsAvailable": 0,
          "lastUpdated": "6/3/2023 6:05:11 AM"
        },
        {
          "date": "08/18/2023_08/20/2023",
          "spotsAvailable": 0,
          "lastUpdated": "6/3/2023 6:05:18 AM"
        },
        {
          "date": "08/25/2023_08/27/2023",
          "spotsAvailable": 0,
          "lastUpdated": "6/3/2023 6:05:26 AM"
        },
        {
          "date": "09/01/2023_09/03/2023",
          "spotsAvailable": 0,
          "lastUpdated": "6/3/2023 6:05:34 AM"
        },
        {
          "date": "09/08/2023_09/10/2023",
          "spotsAvailable": 0,
          "lastUpdated": "6/3/2023 6:05:41 AM"
        },
        {
          "date": "09/15/2023_09/17/2023",
          "spotsAvailable": 0,
          "lastUpdated": "6/3/2023 6:05:49 AM"
        },
        {
          "date": "09/22/2023_09/24/2023",
          "spotsAvailable": 0,
          "lastUpdated": "6/3/2023 6:05:57 AM"
        },
        {
          "date": "09/29/2023_10/01/2023",
          "spotsAvailable": 0,
          "lastUpdated": "6/3/2023 6:06:04 AM"
        },
        {
          "date": "10/06/2023_10/08/2023",
          "spotsAvailable": 0,
          "lastUpdated": "6/3/2023 6:06:12 AM"
        },
        {
          "date": "10/13/2023_10/15/2023",
          "spotsAvailable": 0,
          "lastUpdated": "6/3/2023 6:06:20 AM"
        },
        {
          "date": "10/20/2023_10/22/2023",
          "spotsAvailable": 1,
          "lastUpdated": "6/3/2023 6:06:28 AM"
        },
        {
          "date": "10/27/2023_10/29/2023",
          "spotsAvailable": 6,
          "lastUpdated": "6/3/2023 6:06:36 AM"
        },
        {
          "date": "11/03/2023_11/05/2023",
          "spotsAvailable": 44,
          "lastUpdated": "6/3/2023 6:06:43 AM"
        },
        {
          "date": "11/10/2023_11/12/2023",
          "spotsAvailable": 5,
          "lastUpdated": "6/3/2023 6:06:52 AM"
        },
        {
          "date": "11/17/2023_11/19/2023",
          "spotsAvailable": 34,
          "lastUpdated": "6/3/2023 6:07:00 AM"
        },
        {
          "date": "11/24/2023_11/26/2023",
          "spotsAvailable": 18,
          "lastUpdated": "6/3/2023 6:07:07 AM"
        },
        {
          "date": "12/01/2023_12/03/2023",
          "spotsAvailable": 134,
          "lastUpdated": "6/3/2023 6:07:16 AM"
        }
      ]
    },
    {
      "campground": "new_brigthon_sb",
      "dates": [
        {
          "date": "04/28/2023_04/30/2023",
          "spotsAvailable": 0,
          "lastUpdated": "4/26/2023 2:23:08 PM"
        },
        {
          "date": "05/05/2023_05/07/2023",
          "spotsAvailable": 0,
          "lastUpdated": "5/4/2023 11:59:30 PM"
        },
        {
          "date": "05/12/2023_05/14/2023",
          "spotsAvailable": 0,
          "lastUpdated": "5/11/2023 5:59:37 PM"
        },
        {
          "date": "05/19/2023_05/21/2023",
          "spotsAvailable": 0,
          "lastUpdated": "5/17/2023 4:59:35 PM"
        },
        {
          "date": "05/26/2023_05/28/2023",
          "spotsAvailable": 0,
          "lastUpdated": "5/25/2023 3:59:32 PM"
        },
        {
          "date": "06/02/2023_06/04/2023",
          "spotsAvailable": 0,
          "lastUpdated": "6/1/2023 7:59:34 PM"
        },
        {
          "date": "06/09/2023_06/11/2023",
          "spotsAvailable": 0,
          "lastUpdated": "6/3/2023 1:59:34 AM"
        },
        {
          "date": "06/16/2023_06/18/2023",
          "spotsAvailable": 0,
          "lastUpdated": "6/3/2023 1:59:41 AM"
        },
        {
          "date": "06/23/2023_06/25/2023",
          "spotsAvailable": 0,
          "lastUpdated": "6/3/2023 1:59:50 AM"
        },
        {
          "date": "06/30/2023_07/02/2023",
          "spotsAvailable": 0,
          "lastUpdated": "6/3/2023 1:59:58 AM"
        },
        {
          "date": "07/07/2023_07/09/2023",
          "spotsAvailable": 0,
          "lastUpdated": "6/3/2023 2:00:06 AM"
        },
        {
          "date": "07/14/2023_07/16/2023",
          "spotsAvailable": 0,
          "lastUpdated": "6/3/2023 2:00:13 AM"
        },
        {
          "date": "07/21/2023_07/23/2023",
          "spotsAvailable": 0,
          "lastUpdated": "6/3/2023 2:00:21 AM"
        },
        {
          "date": "07/28/2023_07/30/2023",
          "spotsAvailable": 0,
          "lastUpdated": "6/3/2023 2:00:29 AM"
        },
        {
          "date": "08/04/2023_08/06/2023",
          "spotsAvailable": 0,
          "lastUpdated": "6/3/2023 2:00:37 AM"
        },
        {
          "date": "08/11/2023_08/13/2023",
          "spotsAvailable": 0,
          "lastUpdated": "6/3/2023 2:00:45 AM"
        },
        {
          "date": "08/18/2023_08/20/2023",
          "spotsAvailable": 0,
          "lastUpdated": "6/3/2023 2:00:53 AM"
        },
        {
          "date": "08/25/2023_08/27/2023",
          "spotsAvailable": 0,
          "lastUpdated": "6/3/2023 2:01:01 AM"
        },
        {
          "date": "09/01/2023_09/03/2023",
          "spotsAvailable": 0,
          "lastUpdated": "6/3/2023 2:01:08 AM"
        },
        {
          "date": "09/08/2023_09/10/2023",
          "spotsAvailable": 0,
          "lastUpdated": "6/3/2023 2:01:16 AM"
        },
        {
          "date": "09/15/2023_09/17/2023",
          "spotsAvailable": 0,
          "lastUpdated": "6/3/2023 2:01:24 AM"
        },
        {
          "date": "09/22/2023_09/24/2023",
          "spotsAvailable": 0,
          "lastUpdated": "6/3/2023 2:01:32 AM"
        },
        {
          "date": "09/29/2023_10/01/2023",
          "spotsAvailable": 0,
          "lastUpdated": "6/3/2023 2:01:40 AM"
        },
        {
          "date": "10/06/2023_10/08/2023",
          "spotsAvailable": 0,
          "lastUpdated": "6/3/2023 2:01:47 AM"
        },
        {
          "date": "10/13/2023_10/15/2023",
          "spotsAvailable": 0,
          "lastUpdated": "6/3/2023 2:01:55 AM"
        },
        {
          "date": "10/20/2023_10/22/2023",
          "spotsAvailable": 0,
          "lastUpdated": "6/3/2023 2:02:04 AM"
        },
        {
          "date": "10/27/2023_10/29/2023",
          "spotsAvailable": 0,
          "lastUpdated": "6/3/2023 2:02:12 AM"
        },
        {
          "date": "11/03/2023_11/05/2023",
          "spotsAvailable": 0,
          "lastUpdated": "6/3/2023 2:02:20 AM"
        },
        {
          "date": "11/10/2023_11/12/2023",
          "spotsAvailable": 0,
          "lastUpdated": "6/3/2023 2:02:28 AM"
        },
        {
          "date": "11/17/2023_11/19/2023",
          "spotsAvailable": 0,
          "lastUpdated": "6/3/2023 2:02:36 AM"
        },
        {
          "date": "11/24/2023_11/26/2023",
          "spotsAvailable": 0,
          "lastUpdated": "6/3/2023 2:02:44 AM"
        },
        {
          "date": "12/01/2023_12/03/2023",
          "spotsAvailable": 38,
          "lastUpdated": "6/3/2023 2:02:51 AM"
        }
      ]
    },
    {
      "campground": "morro_bay",
      "dates": [
        {
          "date": "04/28/2023_04/30/2023",
          "spotsAvailable": 0,
          "lastUpdated": "4/26/2023 2:28:14 PM"
        },
        {
          "date": "05/05/2023_05/07/2023",
          "spotsAvailable": 2,
          "lastUpdated": "5/4/2023 11:07:24 PM"
        },
        {
          "date": "05/12/2023_05/14/2023",
          "spotsAvailable": 0,
          "lastUpdated": "5/12/2023 12:07:25 AM"
        },
        {
          "date": "05/19/2023_05/21/2023",
          "spotsAvailable": 0,
          "lastUpdated": "5/18/2023 1:07:31 AM"
        },
        {
          "date": "05/26/2023_05/28/2023",
          "spotsAvailable": 0,
          "lastUpdated": "5/26/2023 12:07:33 AM"
        },
        {
          "date": "06/02/2023_06/04/2023",
          "spotsAvailable": 0,
          "lastUpdated": "6/2/2023 12:05:42 AM"
        },
        {
          "date": "06/09/2023_06/11/2023",
          "spotsAvailable": 0,
          "lastUpdated": "6/3/2023 7:03:59 AM"
        },
        {
          "date": "06/16/2023_06/18/2023",
          "spotsAvailable": 0,
          "lastUpdated": "6/3/2023 7:04:06 AM"
        },
        {
          "date": "06/23/2023_06/25/2023",
          "spotsAvailable": 0,
          "lastUpdated": "6/3/2023 7:04:13 AM"
        },
        {
          "date": "06/30/2023_07/02/2023",
          "spotsAvailable": 0,
          "lastUpdated": "6/3/2023 7:04:22 AM"
        },
        {
          "date": "07/07/2023_07/09/2023",
          "spotsAvailable": 0,
          "lastUpdated": "6/3/2023 7:04:29 AM"
        },
        {
          "date": "07/14/2023_07/16/2023",
          "spotsAvailable": 0,
          "lastUpdated": "6/3/2023 7:04:36 AM"
        },
        {
          "date": "07/21/2023_07/23/2023",
          "spotsAvailable": 0,
          "lastUpdated": "6/3/2023 7:04:44 AM"
        },
        {
          "date": "07/28/2023_07/30/2023",
          "spotsAvailable": 0,
          "lastUpdated": "6/3/2023 7:04:51 AM"
        },
        {
          "date": "08/04/2023_08/06/2023",
          "spotsAvailable": 0,
          "lastUpdated": "6/3/2023 7:04:59 AM"
        },
        {
          "date": "08/11/2023_08/13/2023",
          "spotsAvailable": 0,
          "lastUpdated": "6/3/2023 7:05:06 AM"
        },
        {
          "date": "08/18/2023_08/20/2023",
          "spotsAvailable": 0,
          "lastUpdated": "6/3/2023 7:05:14 AM"
        },
        {
          "date": "08/25/2023_08/27/2023",
          "spotsAvailable": 0,
          "lastUpdated": "6/3/2023 7:05:22 AM"
        },
        {
          "date": "09/01/2023_09/03/2023",
          "spotsAvailable": 0,
          "lastUpdated": "6/3/2023 7:05:30 AM"
        },
        {
          "date": "09/08/2023_09/10/2023",
          "spotsAvailable": 0,
          "lastUpdated": "6/3/2023 7:05:39 AM"
        },
        {
          "date": "09/15/2023_09/17/2023",
          "spotsAvailable": 0,
          "lastUpdated": "6/3/2023 7:05:46 AM"
        },
        {
          "date": "09/22/2023_09/24/2023",
          "spotsAvailable": 0,
          "lastUpdated": "6/3/2023 7:05:54 AM"
        },
        {
          "date": "09/29/2023_10/01/2023",
          "spotsAvailable": 0,
          "lastUpdated": "6/3/2023 7:06:02 AM"
        },
        {
          "date": "10/06/2023_10/08/2023",
          "spotsAvailable": 0,
          "lastUpdated": "6/3/2023 7:06:09 AM"
        },
        {
          "date": "10/13/2023_10/15/2023",
          "spotsAvailable": 0,
          "lastUpdated": "6/3/2023 7:06:16 AM"
        },
        {
          "date": "10/20/2023_10/22/2023",
          "spotsAvailable": 1,
          "lastUpdated": "6/3/2023 7:06:24 AM"
        },
        {
          "date": "10/27/2023_10/29/2023",
          "spotsAvailable": 41,
          "lastUpdated": "6/3/2023 7:06:34 AM"
        },
        {
          "date": "11/03/2023_11/05/2023",
          "spotsAvailable": 35,
          "lastUpdated": "6/3/2023 7:06:41 AM"
        },
        {
          "date": "11/10/2023_11/12/2023",
          "spotsAvailable": 32,
          "lastUpdated": "6/3/2023 7:06:49 AM"
        },
        {
          "date": "11/17/2023_11/19/2023",
          "spotsAvailable": 18,
          "lastUpdated": "6/3/2023 7:06:57 AM"
        },
        {
          "date": "11/24/2023_11/26/2023",
          "spotsAvailable": 2,
          "lastUpdated": "6/3/2023 7:07:06 AM"
        },
        {
          "date": "12/01/2023_12/03/2023",
          "spotsAvailable": 91,
          "lastUpdated": "6/3/2023 7:07:14 AM"
        }
      ]
    },
    {
      "campground": "emma_wood",
      "dates": [
        {
          "date": "04/28/2023_04/30/2023",
          "spotsAvailable": 0,
          "lastUpdated": "4/26/2023 2:31:46 PM"
        },
        {
          "date": "05/05/2023_05/07/2023",
          "spotsAvailable": 0,
          "lastUpdated": "5/4/2023 11:14:17 PM"
        },
        {
          "date": "05/12/2023_05/14/2023",
          "spotsAvailable": 0,
          "lastUpdated": "5/12/2023 12:14:13 AM"
        },
        {
          "date": "05/19/2023_05/21/2023",
          "spotsAvailable": 0,
          "lastUpdated": "5/18/2023 1:14:18 AM"
        },
        {
          "date": "05/26/2023_05/28/2023",
          "spotsAvailable": 0,
          "lastUpdated": "5/26/2023 12:14:15 AM"
        },
        {
          "date": "06/02/2023_06/04/2023",
          "spotsAvailable": 0,
          "lastUpdated": "6/2/2023 12:09:50 AM"
        },
        {
          "date": "06/09/2023_06/11/2023",
          "spotsAvailable": 0,
          "lastUpdated": "6/3/2023 3:10:49 AM"
        },
        {
          "date": "06/16/2023_06/18/2023",
          "spotsAvailable": 0,
          "lastUpdated": "6/3/2023 3:10:59 AM"
        },
        {
          "date": "06/23/2023_06/25/2023",
          "spotsAvailable": 0,
          "lastUpdated": "6/3/2023 3:11:06 AM"
        },
        {
          "date": "06/30/2023_07/02/2023",
          "spotsAvailable": 0,
          "lastUpdated": "6/3/2023 3:11:14 AM"
        },
        {
          "date": "07/07/2023_07/09/2023",
          "spotsAvailable": 0,
          "lastUpdated": "6/3/2023 3:11:21 AM"
        },
        {
          "date": "07/14/2023_07/16/2023",
          "spotsAvailable": 0,
          "lastUpdated": "6/3/2023 3:11:29 AM"
        },
        {
          "date": "07/21/2023_07/23/2023",
          "spotsAvailable": 0,
          "lastUpdated": "6/3/2023 3:11:36 AM"
        },
        {
          "date": "07/28/2023_07/30/2023",
          "spotsAvailable": 2,
          "lastUpdated": "6/3/2023 3:11:44 AM"
        },
        {
          "date": "08/04/2023_08/06/2023",
          "spotsAvailable": 0,
          "lastUpdated": "6/3/2023 3:11:51 AM"
        },
        {
          "date": "08/11/2023_08/13/2023",
          "spotsAvailable": 0,
          "lastUpdated": "6/3/2023 3:11:58 AM"
        },
        {
          "date": "08/18/2023_08/20/2023",
          "spotsAvailable": 1,
          "lastUpdated": "6/3/2023 3:12:07 AM"
        },
        {
          "date": "08/25/2023_08/27/2023",
          "spotsAvailable": 0,
          "lastUpdated": "6/3/2023 3:12:15 AM"
        },
        {
          "date": "09/01/2023_09/03/2023",
          "spotsAvailable": 0,
          "lastUpdated": "6/3/2023 3:12:23 AM"
        },
        {
          "date": "09/08/2023_09/10/2023",
          "spotsAvailable": 0,
          "lastUpdated": "6/3/2023 3:12:31 AM"
        },
        {
          "date": "09/15/2023_09/17/2023",
          "spotsAvailable": 1,
          "lastUpdated": "6/3/2023 3:12:39 AM"
        },
        {
          "date": "09/22/2023_09/24/2023",
          "spotsAvailable": 0,
          "lastUpdated": "6/3/2023 3:12:47 AM"
        },
        {
          "date": "09/29/2023_10/01/2023",
          "spotsAvailable": 1,
          "lastUpdated": "6/3/2023 3:12:54 AM"
        },
        {
          "date": "10/06/2023_10/08/2023",
          "spotsAvailable": 1,
          "lastUpdated": "6/3/2023 3:13:02 AM"
        },
        {
          "date": "10/13/2023_10/15/2023",
          "spotsAvailable": 1,
          "lastUpdated": "6/3/2023 3:13:09 AM"
        },
        {
          "date": "10/20/2023_10/22/2023",
          "spotsAvailable": 1,
          "lastUpdated": "6/3/2023 3:13:17 AM"
        },
        {
          "date": "10/27/2023_10/29/2023",
          "spotsAvailable": 1,
          "lastUpdated": "6/3/2023 3:13:24 AM"
        },
        {
          "date": "11/03/2023_11/05/2023",
          "spotsAvailable": 1,
          "lastUpdated": "6/3/2023 3:13:31 AM"
        },
        {
          "date": "11/10/2023_11/12/2023",
          "spotsAvailable": 1,
          "lastUpdated": "6/3/2023 3:13:39 AM"
        },
        {
          "date": "11/17/2023_11/19/2023",
          "spotsAvailable": 1,
          "lastUpdated": "6/3/2023 3:13:46 AM"
        },
        {
          "date": "11/24/2023_11/26/2023",
          "spotsAvailable": 1,
          "lastUpdated": "6/3/2023 3:13:54 AM"
        },
        {
          "date": "12/01/2023_12/03/2023",
          "spotsAvailable": 1,
          "lastUpdated": "6/3/2023 3:14:01 AM"
        }
      ]
    },
    {
      "campground": "henry_cowell",
      "dates": [
        {
          "date": "04/28/2023_04/30/2023",
          "spotsAvailable": 0,
          "lastUpdated": "4/26/2023 2:33:43 PM"
        },
        {
          "date": "05/05/2023_05/07/2023",
          "spotsAvailable": 0,
          "lastUpdated": "5/4/2023 9:11:12 PM"
        },
        {
          "date": "05/12/2023_05/14/2023",
          "spotsAvailable": 0,
          "lastUpdated": "5/11/2023 6:20:28 PM"
        },
        {
          "date": "05/19/2023_05/21/2023",
          "spotsAvailable": 0,
          "lastUpdated": "5/18/2023 1:21:01 AM"
        },
        {
          "date": "05/26/2023_05/28/2023",
          "spotsAvailable": 0,
          "lastUpdated": "5/25/2023 11:20:54 PM"
        },
        {
          "date": "06/02/2023_06/04/2023",
          "spotsAvailable": 0,
          "lastUpdated": "6/2/2023 12:12:59 AM"
        },
        {
          "date": "06/09/2023_06/11/2023",
          "spotsAvailable": 0,
          "lastUpdated": "6/2/2023 11:10:40 PM"
        },
        {
          "date": "06/16/2023_06/18/2023",
          "spotsAvailable": 0,
          "lastUpdated": "6/2/2023 11:10:48 PM"
        },
        {
          "date": "06/23/2023_06/25/2023",
          "spotsAvailable": 0,
          "lastUpdated": "6/2/2023 11:10:55 PM"
        },
        {
          "date": "06/30/2023_07/02/2023",
          "spotsAvailable": 0,
          "lastUpdated": "6/2/2023 11:11:03 PM"
        },
        {
          "date": "07/07/2023_07/09/2023",
          "spotsAvailable": 0,
          "lastUpdated": "6/2/2023 11:11:11 PM"
        },
        {
          "date": "07/14/2023_07/16/2023",
          "spotsAvailable": 0,
          "lastUpdated": "6/2/2023 11:11:18 PM"
        },
        {
          "date": "07/21/2023_07/23/2023",
          "spotsAvailable": 0,
          "lastUpdated": "6/2/2023 11:11:25 PM"
        },
        {
          "date": "07/28/2023_07/30/2023",
          "spotsAvailable": 0,
          "lastUpdated": "6/2/2023 11:11:34 PM"
        },
        {
          "date": "08/04/2023_08/06/2023",
          "spotsAvailable": 0,
          "lastUpdated": "6/2/2023 11:11:42 PM"
        },
        {
          "date": "08/11/2023_08/13/2023",
          "spotsAvailable": 0,
          "lastUpdated": "6/2/2023 11:11:50 PM"
        },
        {
          "date": "08/18/2023_08/20/2023",
          "spotsAvailable": 0,
          "lastUpdated": "6/2/2023 11:11:58 PM"
        },
        {
          "date": "08/25/2023_08/27/2023",
          "spotsAvailable": 0,
          "lastUpdated": "6/2/2023 11:12:06 PM"
        },
        {
          "date": "09/01/2023_09/03/2023",
          "spotsAvailable": 0,
          "lastUpdated": "6/2/2023 11:12:14 PM"
        },
        {
          "date": "09/08/2023_09/10/2023",
          "spotsAvailable": 0,
          "lastUpdated": "6/2/2023 11:12:23 PM"
        },
        {
          "date": "09/15/2023_09/17/2023",
          "spotsAvailable": 0,
          "lastUpdated": "6/2/2023 11:12:31 PM"
        },
        {
          "date": "09/22/2023_09/24/2023",
          "spotsAvailable": 0,
          "lastUpdated": "6/2/2023 11:12:38 PM"
        },
        {
          "date": "09/29/2023_10/01/2023",
          "spotsAvailable": 0,
          "lastUpdated": "6/2/2023 11:12:46 PM"
        },
        {
          "date": "10/06/2023_10/08/2023",
          "spotsAvailable": 0,
          "lastUpdated": "6/2/2023 11:12:53 PM"
        },
        {
          "date": "10/13/2023_10/15/2023",
          "spotsAvailable": 0,
          "lastUpdated": "6/2/2023 11:13:01 PM"
        },
        {
          "date": "10/20/2023_10/22/2023",
          "spotsAvailable": 0,
          "lastUpdated": "6/2/2023 11:13:08 PM"
        },
        {
          "date": "10/27/2023_10/29/2023",
          "spotsAvailable": 0,
          "lastUpdated": "6/2/2023 11:13:14 PM"
        },
        {
          "date": "11/03/2023_11/05/2023",
          "spotsAvailable": 0,
          "lastUpdated": "6/2/2023 11:13:22 PM"
        },
        {
          "date": "11/10/2023_11/12/2023",
          "spotsAvailable": 0,
          "lastUpdated": "6/2/2023 11:13:29 PM"
        },
        {
          "date": "11/17/2023_11/19/2023",
          "spotsAvailable": 0,
          "lastUpdated": "6/2/2023 11:13:36 PM"
        },
        {
          "date": "11/24/2023_11/26/2023",
          "spotsAvailable": 0,
          "lastUpdated": "6/2/2023 11:13:44 PM"
        },
        {
          "date": "12/01/2023_12/03/2023",
          "spotsAvailable": 0,
          "lastUpdated": "6/2/2023 11:13:51 PM"
        }
      ]
    },
    {
      "campground": "leo_carillo",
      "dates": [
        {
          "date": "05/05/2023_05/07/2023",
          "spotsAvailable": 0,
          "lastUpdated": "5/4/2023 11:10:54 PM"
        },
        {
          "date": "05/12/2023_05/14/2023",
          "spotsAvailable": 0,
          "lastUpdated": "5/12/2023 12:10:50 AM"
        },
        {
          "date": "05/19/2023_05/21/2023",
          "spotsAvailable": 0,
          "lastUpdated": "5/18/2023 1:10:57 AM"
        },
        {
          "date": "05/26/2023_05/28/2023",
          "spotsAvailable": 0,
          "lastUpdated": "5/26/2023 12:10:55 AM"
        },
        {
          "date": "06/02/2023_06/04/2023",
          "spotsAvailable": 0,
          "lastUpdated": "6/1/2023 11:07:22 PM"
        },
        {
          "date": "06/09/2023_06/11/2023",
          "spotsAvailable": 0,
          "lastUpdated": "6/3/2023 7:07:25 AM"
        },
        {
          "date": "06/16/2023_06/18/2023",
          "spotsAvailable": 0,
          "lastUpdated": "6/3/2023 7:07:32 AM"
        },
        {
          "date": "06/23/2023_06/25/2023",
          "spotsAvailable": 0,
          "lastUpdated": "6/3/2023 7:07:39 AM"
        },
        {
          "date": "06/30/2023_07/02/2023",
          "spotsAvailable": 0,
          "lastUpdated": "6/3/2023 7:07:47 AM"
        },
        {
          "date": "07/07/2023_07/09/2023",
          "spotsAvailable": 0,
          "lastUpdated": "6/3/2023 7:07:55 AM"
        },
        {
          "date": "07/14/2023_07/16/2023",
          "spotsAvailable": 0,
          "lastUpdated": "6/3/2023 7:08:03 AM"
        },
        {
          "date": "07/21/2023_07/23/2023",
          "spotsAvailable": 0,
          "lastUpdated": "6/3/2023 7:08:10 AM"
        },
        {
          "date": "07/28/2023_07/30/2023",
          "spotsAvailable": 0,
          "lastUpdated": "6/3/2023 7:08:18 AM"
        },
        {
          "date": "08/04/2023_08/06/2023",
          "spotsAvailable": 0,
          "lastUpdated": "6/3/2023 7:08:25 AM"
        },
        {
          "date": "08/11/2023_08/13/2023",
          "spotsAvailable": 0,
          "lastUpdated": "6/3/2023 7:08:32 AM"
        },
        {
          "date": "08/18/2023_08/20/2023",
          "spotsAvailable": 0,
          "lastUpdated": "6/3/2023 7:08:39 AM"
        },
        {
          "date": "08/25/2023_08/27/2023",
          "spotsAvailable": 0,
          "lastUpdated": "6/3/2023 7:08:47 AM"
        },
        {
          "date": "09/01/2023_09/03/2023",
          "spotsAvailable": 0,
          "lastUpdated": "6/3/2023 7:08:54 AM"
        },
        {
          "date": "09/08/2023_09/10/2023",
          "spotsAvailable": 0,
          "lastUpdated": "6/3/2023 7:09:02 AM"
        },
        {
          "date": "09/15/2023_09/17/2023",
          "spotsAvailable": 0,
          "lastUpdated": "6/3/2023 7:09:09 AM"
        },
        {
          "date": "09/22/2023_09/24/2023",
          "spotsAvailable": 0,
          "lastUpdated": "6/3/2023 7:09:17 AM"
        },
        {
          "date": "09/29/2023_10/01/2023",
          "spotsAvailable": 0,
          "lastUpdated": "6/3/2023 7:09:25 AM"
        },
        {
          "date": "10/06/2023_10/08/2023",
          "spotsAvailable": 0,
          "lastUpdated": "6/3/2023 7:09:33 AM"
        },
        {
          "date": "10/13/2023_10/15/2023",
          "spotsAvailable": 0,
          "lastUpdated": "6/3/2023 7:09:42 AM"
        },
        {
          "date": "10/20/2023_10/22/2023",
          "spotsAvailable": 0,
          "lastUpdated": "6/3/2023 7:09:50 AM"
        },
        {
          "date": "10/27/2023_10/29/2023",
          "spotsAvailable": 0,
          "lastUpdated": "6/3/2023 7:09:58 AM"
        },
        {
          "date": "11/03/2023_11/05/2023",
          "spotsAvailable": 0,
          "lastUpdated": "6/3/2023 7:10:06 AM"
        },
        {
          "date": "11/10/2023_11/12/2023",
          "spotsAvailable": 0,
          "lastUpdated": "6/3/2023 7:10:14 AM"
        },
        {
          "date": "11/17/2023_11/19/2023",
          "spotsAvailable": 30,
          "lastUpdated": "6/3/2023 7:10:21 AM"
        },
        {
          "date": "11/24/2023_11/26/2023",
          "spotsAvailable": 3,
          "lastUpdated": "6/3/2023 7:10:30 AM"
        },
        {
          "date": "12/01/2023_12/03/2023",
          "spotsAvailable": 3,
          "lastUpdated": "6/2/2023 9:10:47 PM"
        }
      ]
    },
    {
      "campground": "south_carlsbad_sb",
      "dates": [
        {
          "date": "05/05/2023_05/07/2023",
          "spotsAvailable": 0,
          "lastUpdated": "5/4/2023 11:17:34 PM"
        },
        {
          "date": "05/12/2023_05/14/2023",
          "spotsAvailable": 0,
          "lastUpdated": "5/11/2023 7:05:16 PM"
        },
        {
          "date": "05/19/2023_05/21/2023",
          "spotsAvailable": 0,
          "lastUpdated": "5/18/2023 1:17:41 AM"
        },
        {
          "date": "05/26/2023_05/28/2023",
          "spotsAvailable": 0,
          "lastUpdated": "5/26/2023 12:17:33 AM"
        },
        {
          "date": "06/02/2023_06/04/2023",
          "spotsAvailable": 0,
          "lastUpdated": "6/2/2023 12:11:32 AM"
        },
        {
          "date": "06/09/2023_06/11/2023",
          "spotsAvailable": 0,
          "lastUpdated": "6/3/2023 3:14:12 AM"
        },
        {
          "date": "06/16/2023_06/18/2023",
          "spotsAvailable": 0,
          "lastUpdated": "6/3/2023 3:14:20 AM"
        },
        {
          "date": "06/23/2023_06/25/2023",
          "spotsAvailable": 0,
          "lastUpdated": "6/3/2023 3:14:27 AM"
        },
        {
          "date": "06/30/2023_07/02/2023",
          "spotsAvailable": 0,
          "lastUpdated": "6/3/2023 3:14:34 AM"
        },
        {
          "date": "07/07/2023_07/09/2023",
          "spotsAvailable": 0,
          "lastUpdated": "6/3/2023 3:14:42 AM"
        },
        {
          "date": "07/14/2023_07/16/2023",
          "spotsAvailable": 0,
          "lastUpdated": "6/3/2023 3:14:50 AM"
        },
        {
          "date": "07/21/2023_07/23/2023",
          "spotsAvailable": 0,
          "lastUpdated": "6/3/2023 3:14:58 AM"
        },
        {
          "date": "07/28/2023_07/30/2023",
          "spotsAvailable": 0,
          "lastUpdated": "6/3/2023 3:15:06 AM"
        },
        {
          "date": "08/04/2023_08/06/2023",
          "spotsAvailable": 0,
          "lastUpdated": "6/3/2023 3:15:13 AM"
        },
        {
          "date": "08/11/2023_08/13/2023",
          "spotsAvailable": 0,
          "lastUpdated": "6/3/2023 3:15:21 AM"
        },
        {
          "date": "08/18/2023_08/20/2023",
          "spotsAvailable": 0,
          "lastUpdated": "6/3/2023 3:15:29 AM"
        },
        {
          "date": "08/25/2023_08/27/2023",
          "spotsAvailable": 0,
          "lastUpdated": "6/3/2023 3:15:37 AM"
        },
        {
          "date": "09/01/2023_09/03/2023",
          "spotsAvailable": 0,
          "lastUpdated": "6/2/2023 10:12:30 PM"
        },
        {
          "date": "09/08/2023_09/10/2023",
          "spotsAvailable": 0,
          "lastUpdated": "6/2/2023 10:12:38 PM"
        },
        {
          "date": "09/15/2023_09/17/2023",
          "spotsAvailable": 0,
          "lastUpdated": "6/2/2023 10:12:46 PM"
        },
        {
          "date": "09/22/2023_09/24/2023",
          "spotsAvailable": 0,
          "lastUpdated": "6/2/2023 10:12:53 PM"
        },
        {
          "date": "09/29/2023_10/01/2023",
          "spotsAvailable": 0,
          "lastUpdated": "6/2/2023 10:13:02 PM"
        },
        {
          "date": "10/06/2023_10/08/2023",
          "spotsAvailable": 0,
          "lastUpdated": "6/2/2023 4:22:05 PM"
        },
        {
          "date": "10/13/2023_10/15/2023",
          "spotsAvailable": 0,
          "lastUpdated": "6/2/2023 4:22:12 PM"
        },
        {
          "date": "10/20/2023_10/22/2023",
          "spotsAvailable": 0,
          "lastUpdated": "6/2/2023 4:22:19 PM"
        },
        {
          "date": "10/27/2023_10/29/2023",
          "spotsAvailable": 0,
          "lastUpdated": "6/2/2023 4:22:27 PM"
        },
        {
          "date": "11/03/2023_11/05/2023",
          "spotsAvailable": 0,
          "lastUpdated": "6/2/2023 4:22:34 PM"
        },
        {
          "date": "11/10/2023_11/12/2023",
          "spotsAvailable": 0,
          "lastUpdated": "6/2/2023 4:22:41 PM"
        },
        {
          "date": "11/17/2023_11/19/2023",
          "spotsAvailable": 0,
          "lastUpdated": "6/2/2023 4:22:48 PM"
        },
        {
          "date": "11/24/2023_11/26/2023",
          "spotsAvailable": 0,
          "lastUpdated": "6/2/2023 4:22:55 PM"
        },
        {
          "date": "12/01/2023_12/03/2023",
          "spotsAvailable": 0,
          "lastUpdated": "6/2/2023 4:23:02 PM"
        }
      ]
    }
  ]
}