{
  "campground_dates": [
    {
      "campground": "pfeiffer",
      "dates": [
        {
          "date": "04/28/2023_04/30/2023",
          "spotsAvailable": 0,
          "lastUpdated": "4/26/2023 2:24:02 PM"
        },
        {
          "date": "05/05/2023_05/07/2023",
          "spotsAvailable": 0,
          "lastUpdated": "5/4/2023 11:00:33 PM"
        },
        {
          "date": "05/12/2023_05/14/2023",
          "spotsAvailable": 0,
          "lastUpdated": "5/12/2023 12:00:37 AM"
        },
        {
          "date": "05/19/2023_05/21/2023",
          "spotsAvailable": 0,
          "lastUpdated": "5/18/2023 2:00:33 AM"
        },
        {
          "date": "05/26/2023_05/28/2023",
          "spotsAvailable": 0,
          "lastUpdated": "5/26/2023 12:00:34 AM"
        },
        {
          "date": "06/02/2023_06/04/2023",
          "spotsAvailable": 0,
          "lastUpdated": "6/2/2023 12:00:36 AM"
        },
        {
          "date": "06/09/2023_06/11/2023",
          "spotsAvailable": 0,
          "lastUpdated": "6/9/2023 12:00:32 AM"
        },
        {
          "date": "06/16/2023_06/18/2023",
          "spotsAvailable": 0,
          "lastUpdated": "6/9/2023 5:00:32 PM"
        },
        {
          "date": "06/23/2023_06/25/2023",
          "spotsAvailable": 0,
          "lastUpdated": "6/9/2023 5:00:39 PM"
        },
        {
          "date": "06/30/2023_07/02/2023",
          "spotsAvailable": 0,
          "lastUpdated": "6/9/2023 5:00:47 PM"
        },
        {
          "date": "07/07/2023_07/09/2023",
          "spotsAvailable": 0,
          "lastUpdated": "6/9/2023 5:00:54 PM"
        },
        {
          "date": "07/14/2023_07/16/2023",
          "spotsAvailable": 0,
          "lastUpdated": "6/9/2023 5:01:03 PM"
        },
        {
          "date": "07/21/2023_07/23/2023",
          "spotsAvailable": 0,
          "lastUpdated": "6/9/2023 5:01:11 PM"
        },
        {
          "date": "07/28/2023_07/30/2023",
          "spotsAvailable": 0,
          "lastUpdated": "6/9/2023 5:01:20 PM"
        },
        {
          "date": "08/04/2023_08/06/2023",
          "spotsAvailable": 0,
          "lastUpdated": "6/9/2023 5:01:28 PM"
        },
        {
          "date": "08/11/2023_08/13/2023",
          "spotsAvailable": 0,
          "lastUpdated": "6/9/2023 5:01:36 PM"
        },
        {
          "date": "08/18/2023_08/20/2023",
          "spotsAvailable": 0,
          "lastUpdated": "6/9/2023 5:01:44 PM"
        },
        {
          "date": "08/25/2023_08/27/2023",
          "spotsAvailable": 0,
          "lastUpdated": "6/9/2023 5:01:52 PM"
        },
        {
          "date": "09/01/2023_09/03/2023",
          "spotsAvailable": 0,
          "lastUpdated": "6/9/2023 5:02:01 PM"
        },
        {
          "date": "09/08/2023_09/10/2023",
          "spotsAvailable": 0,
          "lastUpdated": "6/9/2023 5:02:08 PM"
        },
        {
          "date": "09/15/2023_09/17/2023",
          "spotsAvailable": 0,
          "lastUpdated": "6/9/2023 5:02:17 PM"
        },
        {
          "date": "09/22/2023_09/24/2023",
          "spotsAvailable": 0,
          "lastUpdated": "6/9/2023 5:02:26 PM"
        },
        {
          "date": "09/29/2023_10/01/2023",
          "spotsAvailable": 0,
          "lastUpdated": "6/9/2023 5:02:34 PM"
        },
        {
          "date": "10/06/2023_10/08/2023",
          "spotsAvailable": 0,
          "lastUpdated": "6/9/2023 5:02:42 PM"
        },
        {
          "date": "10/13/2023_10/15/2023",
          "spotsAvailable": 0,
          "lastUpdated": "6/9/2023 5:02:50 PM"
        },
        {
          "date": "10/20/2023_10/22/2023",
          "spotsAvailable": 0,
          "lastUpdated": "6/9/2023 5:02:57 PM"
        },
        {
          "date": "10/27/2023_10/29/2023",
          "spotsAvailable": 0,
          "lastUpdated": "6/9/2023 5:03:06 PM"
        },
        {
          "date": "11/03/2023_11/05/2023",
          "spotsAvailable": 19,
          "lastUpdated": "6/9/2023 5:03:14 PM"
        },
        {
          "date": "11/10/2023_11/12/2023",
          "spotsAvailable": 35,
          "lastUpdated": "6/9/2023 5:03:22 PM"
        },
        {
          "date": "11/17/2023_11/19/2023",
          "spotsAvailable": 43,
          "lastUpdated": "6/9/2023 5:03:30 PM"
        },
        {
          "date": "11/24/2023_11/26/2023",
          "spotsAvailable": 47,
          "lastUpdated": "6/9/2023 5:03:38 PM"
        },
        {
          "date": "12/01/2023_12/03/2023",
          "spotsAvailable": 38,
          "lastUpdated": "6/9/2023 5:03:46 PM"
        },
        {
          "date": "12/08/2023_12/10/2023",
          "spotsAvailable": 39,
          "lastUpdated": "6/9/2023 5:03:54 PM"
        }
      ]
    },
    {
      "campground": "carpinteria",
      "dates": [
        {
          "date": "04/28/2023_04/30/2023",
          "spotsAvailable": 0,
          "lastUpdated": "4/26/2023 2:25:26 PM"
        },
        {
          "date": "05/05/2023_05/07/2023",
          "spotsAvailable": 2,
          "lastUpdated": "5/4/2023 11:04:01 PM"
        },
        {
          "date": "05/12/2023_05/14/2023",
          "spotsAvailable": 0,
          "lastUpdated": "5/12/2023 12:04:02 AM"
        },
        {
          "date": "05/19/2023_05/21/2023",
          "spotsAvailable": 0,
          "lastUpdated": "5/18/2023 1:04:05 AM"
        },
        {
          "date": "05/26/2023_05/28/2023",
          "spotsAvailable": 0,
          "lastUpdated": "5/26/2023 12:04:07 AM"
        },
        {
          "date": "06/02/2023_06/04/2023",
          "spotsAvailable": 0,
          "lastUpdated": "6/2/2023 12:02:14 AM"
        },
        {
          "date": "06/09/2023_06/11/2023",
          "spotsAvailable": 0,
          "lastUpdated": "6/9/2023 12:04:01 AM"
        },
        {
          "date": "06/16/2023_06/18/2023",
          "spotsAvailable": 0,
          "lastUpdated": "6/9/2023 5:04:05 PM"
        },
        {
          "date": "06/23/2023_06/25/2023",
          "spotsAvailable": 0,
          "lastUpdated": "6/9/2023 5:04:13 PM"
        },
        {
          "date": "06/30/2023_07/02/2023",
          "spotsAvailable": 0,
          "lastUpdated": "6/9/2023 5:04:21 PM"
        },
        {
          "date": "07/07/2023_07/09/2023",
          "spotsAvailable": 0,
          "lastUpdated": "6/9/2023 5:04:28 PM"
        },
        {
          "date": "07/14/2023_07/16/2023",
          "spotsAvailable": 0,
          "lastUpdated": "6/9/2023 5:04:36 PM"
        },
        {
          "date": "07/21/2023_07/23/2023",
          "spotsAvailable": 0,
          "lastUpdated": "6/9/2023 5:04:43 PM"
        },
        {
          "date": "07/28/2023_07/30/2023",
          "spotsAvailable": 0,
          "lastUpdated": "6/9/2023 5:04:52 PM"
        },
        {
          "date": "08/04/2023_08/06/2023",
          "spotsAvailable": 0,
          "lastUpdated": "6/9/2023 5:04:59 PM"
        },
        {
          "date": "08/11/2023_08/13/2023",
          "spotsAvailable": 0,
          "lastUpdated": "6/9/2023 5:05:08 PM"
        },
        {
          "date": "08/18/2023_08/20/2023",
          "spotsAvailable": 0,
          "lastUpdated": "6/9/2023 5:05:14 PM"
        },
        {
          "date": "08/25/2023_08/27/2023",
          "spotsAvailable": 0,
          "lastUpdated": "6/9/2023 5:05:22 PM"
        },
        {
          "date": "09/01/2023_09/03/2023",
          "spotsAvailable": 0,
          "lastUpdated": "6/9/2023 5:05:30 PM"
        },
        {
          "date": "09/08/2023_09/10/2023",
          "spotsAvailable": 0,
          "lastUpdated": "6/9/2023 5:05:37 PM"
        },
        {
          "date": "09/15/2023_09/17/2023",
          "spotsAvailable": 0,
          "lastUpdated": "6/9/2023 5:05:46 PM"
        },
        {
          "date": "09/22/2023_09/24/2023",
          "spotsAvailable": 0,
          "lastUpdated": "6/9/2023 5:05:54 PM"
        },
        {
          "date": "09/29/2023_10/01/2023",
          "spotsAvailable": 0,
          "lastUpdated": "6/9/2023 5:06:01 PM"
        },
        {
          "date": "10/06/2023_10/08/2023",
          "spotsAvailable": 0,
          "lastUpdated": "6/9/2023 5:06:09 PM"
        },
        {
          "date": "10/13/2023_10/15/2023",
          "spotsAvailable": 0,
          "lastUpdated": "6/9/2023 5:06:16 PM"
        },
        {
          "date": "10/20/2023_10/22/2023",
          "spotsAvailable": 0,
          "lastUpdated": "6/9/2023 5:06:24 PM"
        },
        {
          "date": "10/27/2023_10/29/2023",
          "spotsAvailable": 4,
          "lastUpdated": "6/9/2023 5:06:33 PM"
        },
        {
          "date": "11/03/2023_11/05/2023",
          "spotsAvailable": 43,
          "lastUpdated": "6/9/2023 5:06:40 PM"
        },
        {
          "date": "11/10/2023_11/12/2023",
          "spotsAvailable": 1,
          "lastUpdated": "6/9/2023 5:06:47 PM"
        },
        {
          "date": "11/17/2023_11/19/2023",
          "spotsAvailable": 31,
          "lastUpdated": "6/9/2023 5:06:56 PM"
        },
        {
          "date": "11/24/2023_11/26/2023",
          "spotsAvailable": 16,
          "lastUpdated": "6/9/2023 5:07:05 PM"
        },
        {
          "date": "12/01/2023_12/03/2023",
          "spotsAvailable": 118,
          "lastUpdated": "6/9/2023 5:07:12 PM"
        },
        {
          "date": "12/08/2023_12/10/2023",
          "spotsAvailable": 130,
          "lastUpdated": "6/9/2023 5:07:20 PM"
        }
      ]
    },
    {
      "campground": "new_brigthon_sb",
      "dates": [
        {
          "date": "04/28/2023_04/30/2023",
          "spotsAvailable": 0,
          "lastUpdated": "4/26/2023 2:23:08 PM"
        },
        {
          "date": "05/05/2023_05/07/2023",
          "spotsAvailable": 0,
          "lastUpdated": "5/4/2023 11:59:30 PM"
        },
        {
          "date": "05/12/2023_05/14/2023",
          "spotsAvailable": 0,
          "lastUpdated": "5/11/2023 5:59:37 PM"
        },
        {
          "date": "05/19/2023_05/21/2023",
          "spotsAvailable": 0,
          "lastUpdated": "5/17/2023 4:59:35 PM"
        },
        {
          "date": "05/26/2023_05/28/2023",
          "spotsAvailable": 0,
          "lastUpdated": "5/25/2023 3:59:32 PM"
        },
        {
          "date": "06/02/2023_06/04/2023",
          "spotsAvailable": 0,
          "lastUpdated": "6/1/2023 7:59:34 PM"
        },
        {
          "date": "06/09/2023_06/11/2023",
          "spotsAvailable": 0,
          "lastUpdated": "6/8/2023 6:59:41 PM"
        },
        {
          "date": "06/16/2023_06/18/2023",
          "spotsAvailable": 0,
          "lastUpdated": "6/9/2023 2:59:40 PM"
        },
        {
          "date": "06/23/2023_06/25/2023",
          "spotsAvailable": 0,
          "lastUpdated": "6/9/2023 2:59:48 PM"
        },
        {
          "date": "06/30/2023_07/02/2023",
          "spotsAvailable": 0,
          "lastUpdated": "6/9/2023 2:59:57 PM"
        },
        {
          "date": "07/07/2023_07/09/2023",
          "spotsAvailable": 0,
          "lastUpdated": "6/9/2023 3:00:05 PM"
        },
        {
          "date": "07/14/2023_07/16/2023",
          "spotsAvailable": 0,
          "lastUpdated": "6/9/2023 3:00:13 PM"
        },
        {
          "date": "07/21/2023_07/23/2023",
          "spotsAvailable": 0,
          "lastUpdated": "6/9/2023 3:00:21 PM"
        },
        {
          "date": "07/28/2023_07/30/2023",
          "spotsAvailable": 0,
          "lastUpdated": "6/9/2023 3:00:29 PM"
        },
        {
          "date": "08/04/2023_08/06/2023",
          "spotsAvailable": 0,
          "lastUpdated": "6/9/2023 3:00:37 PM"
        },
        {
          "date": "08/11/2023_08/13/2023",
          "spotsAvailable": 0,
          "lastUpdated": "6/9/2023 3:00:45 PM"
        },
        {
          "date": "08/18/2023_08/20/2023",
          "spotsAvailable": 0,
          "lastUpdated": "6/9/2023 3:00:53 PM"
        },
        {
          "date": "08/25/2023_08/27/2023",
          "spotsAvailable": 0,
          "lastUpdated": "6/9/2023 3:01:00 PM"
        },
        {
          "date": "09/01/2023_09/03/2023",
          "spotsAvailable": 0,
          "lastUpdated": "6/9/2023 3:01:10 PM"
        },
        {
          "date": "09/08/2023_09/10/2023",
          "spotsAvailable": 0,
          "lastUpdated": "6/9/2023 3:01:18 PM"
        },
        {
          "date": "09/15/2023_09/17/2023",
          "spotsAvailable": 0,
          "lastUpdated": "6/9/2023 3:01:27 PM"
        },
        {
          "date": "09/22/2023_09/24/2023",
          "spotsAvailable": 0,
          "lastUpdated": "6/9/2023 3:01:34 PM"
        },
        {
          "date": "09/29/2023_10/01/2023",
          "spotsAvailable": 0,
          "lastUpdated": "6/9/2023 3:01:41 PM"
        },
        {
          "date": "10/06/2023_10/08/2023",
          "spotsAvailable": 0,
          "lastUpdated": "6/9/2023 3:01:49 PM"
        },
        {
          "date": "10/13/2023_10/15/2023",
          "spotsAvailable": 0,
          "lastUpdated": "6/9/2023 3:01:57 PM"
        },
        {
          "date": "10/20/2023_10/22/2023",
          "spotsAvailable": 0,
          "lastUpdated": "6/9/2023 3:02:05 PM"
        },
        {
          "date": "10/27/2023_10/29/2023",
          "spotsAvailable": 0,
          "lastUpdated": "6/9/2023 3:02:12 PM"
        },
        {
          "date": "11/03/2023_11/05/2023",
          "spotsAvailable": 0,
          "lastUpdated": "6/9/2023 3:02:20 PM"
        },
        {
          "date": "11/10/2023_11/12/2023",
          "spotsAvailable": 0,
          "lastUpdated": "6/9/2023 3:02:28 PM"
        },
        {
          "date": "11/17/2023_11/19/2023",
          "spotsAvailable": 0,
          "lastUpdated": "6/9/2023 3:02:35 PM"
        },
        {
          "date": "11/24/2023_11/26/2023",
          "spotsAvailable": 0,
          "lastUpdated": "6/9/2023 3:02:43 PM"
        },
        {
          "date": "12/01/2023_12/03/2023",
          "spotsAvailable": 25,
          "lastUpdated": "6/9/2023 3:02:51 PM"
        },
        {
          "date": "12/08/2023_12/10/2023",
          "spotsAvailable": 33,
          "lastUpdated": "6/9/2023 3:02:59 PM"
        }
      ]
    },
    {
      "campground": "morro_bay",
      "dates": [
        {
          "date": "04/28/2023_04/30/2023",
          "spotsAvailable": 0,
          "lastUpdated": "4/26/2023 2:28:14 PM"
        },
        {
          "date": "05/05/2023_05/07/2023",
          "spotsAvailable": 2,
          "lastUpdated": "5/4/2023 11:07:24 PM"
        },
        {
          "date": "05/12/2023_05/14/2023",
          "spotsAvailable": 0,
          "lastUpdated": "5/12/2023 12:07:25 AM"
        },
        {
          "date": "05/19/2023_05/21/2023",
          "spotsAvailable": 0,
          "lastUpdated": "5/18/2023 1:07:31 AM"
        },
        {
          "date": "05/26/2023_05/28/2023",
          "spotsAvailable": 0,
          "lastUpdated": "5/26/2023 12:07:33 AM"
        },
        {
          "date": "06/02/2023_06/04/2023",
          "spotsAvailable": 0,
          "lastUpdated": "6/2/2023 12:05:42 AM"
        },
        {
          "date": "06/09/2023_06/11/2023",
          "spotsAvailable": 0,
          "lastUpdated": "6/8/2023 11:07:37 PM"
        },
        {
          "date": "06/16/2023_06/18/2023",
          "spotsAvailable": 0,
          "lastUpdated": "6/9/2023 4:07:08 PM"
        },
        {
          "date": "06/23/2023_06/25/2023",
          "spotsAvailable": 0,
          "lastUpdated": "6/9/2023 4:07:16 PM"
        },
        {
          "date": "06/30/2023_07/02/2023",
          "spotsAvailable": 1,
          "lastUpdated": "6/9/2023 4:07:24 PM"
        },
        {
          "date": "07/07/2023_07/09/2023",
          "spotsAvailable": 0,
          "lastUpdated": "6/9/2023 4:07:33 PM"
        },
        {
          "date": "07/14/2023_07/16/2023",
          "spotsAvailable": 0,
          "lastUpdated": "6/9/2023 4:07:41 PM"
        },
        {
          "date": "07/21/2023_07/23/2023",
          "spotsAvailable": 0,
          "lastUpdated": "6/9/2023 4:07:48 PM"
        },
        {
          "date": "07/28/2023_07/30/2023",
          "spotsAvailable": 0,
          "lastUpdated": "6/9/2023 4:07:56 PM"
        },
        {
          "date": "08/04/2023_08/06/2023",
          "spotsAvailable": 0,
          "lastUpdated": "6/9/2023 4:08:05 PM"
        },
        {
          "date": "08/11/2023_08/13/2023",
          "spotsAvailable": 0,
          "lastUpdated": "6/9/2023 4:08:12 PM"
        },
        {
          "date": "08/18/2023_08/20/2023",
          "spotsAvailable": 0,
          "lastUpdated": "6/9/2023 4:08:19 PM"
        },
        {
          "date": "08/25/2023_08/27/2023",
          "spotsAvailable": 0,
          "lastUpdated": "6/9/2023 4:08:27 PM"
        },
        {
          "date": "09/01/2023_09/03/2023",
          "spotsAvailable": 0,
          "lastUpdated": "6/9/2023 4:08:34 PM"
        },
        {
          "date": "09/08/2023_09/10/2023",
          "spotsAvailable": 0,
          "lastUpdated": "6/9/2023 4:08:42 PM"
        },
        {
          "date": "09/15/2023_09/17/2023",
          "spotsAvailable": 0,
          "lastUpdated": "6/9/2023 4:08:49 PM"
        },
        {
          "date": "09/22/2023_09/24/2023",
          "spotsAvailable": 0,
          "lastUpdated": "6/9/2023 4:08:57 PM"
        },
        {
          "date": "09/29/2023_10/01/2023",
          "spotsAvailable": 0,
          "lastUpdated": "6/9/2023 4:09:04 PM"
        },
        {
          "date": "10/06/2023_10/08/2023",
          "spotsAvailable": 0,
          "lastUpdated": "6/9/2023 4:09:12 PM"
        },
        {
          "date": "10/13/2023_10/15/2023",
          "spotsAvailable": 0,
          "lastUpdated": "6/9/2023 4:09:19 PM"
        },
        {
          "date": "10/20/2023_10/22/2023",
          "spotsAvailable": 0,
          "lastUpdated": "6/9/2023 4:09:27 PM"
        },
        {
          "date": "10/27/2023_10/29/2023",
          "spotsAvailable": 40,
          "lastUpdated": "6/9/2023 4:09:36 PM"
        },
        {
          "date": "11/03/2023_11/05/2023",
          "spotsAvailable": 33,
          "lastUpdated": "6/9/2023 4:09:45 PM"
        },
        {
          "date": "11/10/2023_11/12/2023",
          "spotsAvailable": 21,
          "lastUpdated": "6/9/2023 4:09:52 PM"
        },
        {
          "date": "11/17/2023_11/19/2023",
          "spotsAvailable": 19,
          "lastUpdated": "6/9/2023 4:10:00 PM"
        },
        {
          "date": "11/24/2023_11/26/2023",
          "spotsAvailable": 2,
          "lastUpdated": "6/9/2023 4:10:08 PM"
        },
        {
          "date": "12/01/2023_12/03/2023",
          "spotsAvailable": 2,
          "lastUpdated": "6/9/2023 4:10:15 PM"
        },
        {
          "date": "12/08/2023_12/10/2023",
          "spotsAvailable": 2,
          "lastUpdated": "6/9/2023 4:10:23 PM"
        }
      ]
    },
    {
      "campground": "emma_wood",
      "dates": [
        {
          "date": "04/28/2023_04/30/2023",
          "spotsAvailable": 0,
          "lastUpdated": "4/26/2023 2:31:46 PM"
        },
        {
          "date": "05/05/2023_05/07/2023",
          "spotsAvailable": 0,
          "lastUpdated": "5/4/2023 11:14:17 PM"
        },
        {
          "date": "05/12/2023_05/14/2023",
          "spotsAvailable": 0,
          "lastUpdated": "5/12/2023 12:14:13 AM"
        },
        {
          "date": "05/19/2023_05/21/2023",
          "spotsAvailable": 0,
          "lastUpdated": "5/18/2023 1:14:18 AM"
        },
        {
          "date": "05/26/2023_05/28/2023",
          "spotsAvailable": 0,
          "lastUpdated": "5/26/2023 12:14:15 AM"
        },
        {
          "date": "06/02/2023_06/04/2023",
          "spotsAvailable": 0,
          "lastUpdated": "6/2/2023 12:09:50 AM"
        },
        {
          "date": "06/09/2023_06/11/2023",
          "spotsAvailable": 0,
          "lastUpdated": "6/9/2023 12:10:53 AM"
        },
        {
          "date": "06/16/2023_06/18/2023",
          "spotsAvailable": 0,
          "lastUpdated": "6/9/2023 4:13:57 PM"
        },
        {
          "date": "06/23/2023_06/25/2023",
          "spotsAvailable": 0,
          "lastUpdated": "6/9/2023 4:14:04 PM"
        },
        {
          "date": "06/30/2023_07/02/2023",
          "spotsAvailable": 0,
          "lastUpdated": "6/9/2023 4:14:12 PM"
        },
        {
          "date": "07/07/2023_07/09/2023",
          "spotsAvailable": 2,
          "lastUpdated": "6/9/2023 4:14:20 PM"
        },
        {
          "date": "07/14/2023_07/16/2023",
          "spotsAvailable": 0,
          "lastUpdated": "6/9/2023 4:14:29 PM"
        },
        {
          "date": "07/21/2023_07/23/2023",
          "spotsAvailable": 0,
          "lastUpdated": "6/9/2023 4:14:37 PM"
        },
        {
          "date": "07/28/2023_07/30/2023",
          "spotsAvailable": 0,
          "lastUpdated": "6/9/2023 4:14:45 PM"
        },
        {
          "date": "08/04/2023_08/06/2023",
          "spotsAvailable": 0,
          "lastUpdated": "6/9/2023 4:14:52 PM"
        },
        {
          "date": "08/11/2023_08/13/2023",
          "spotsAvailable": 0,
          "lastUpdated": "6/9/2023 4:14:59 PM"
        },
        {
          "date": "08/18/2023_08/20/2023",
          "spotsAvailable": 1,
          "lastUpdated": "6/9/2023 4:15:07 PM"
        },
        {
          "date": "08/25/2023_08/27/2023",
          "spotsAvailable": 0,
          "lastUpdated": "6/9/2023 4:15:14 PM"
        },
        {
          "date": "09/01/2023_09/03/2023",
          "spotsAvailable": 0,
          "lastUpdated": "6/9/2023 4:15:22 PM"
        },
        {
          "date": "09/08/2023_09/10/2023",
          "spotsAvailable": 0,
          "lastUpdated": "6/9/2023 4:15:30 PM"
        },
        {
          "date": "09/15/2023_09/17/2023",
          "spotsAvailable": 0,
          "lastUpdated": "6/9/2023 4:15:37 PM"
        },
        {
          "date": "09/22/2023_09/24/2023",
          "spotsAvailable": 0,
          "lastUpdated": "6/9/2023 4:15:44 PM"
        },
        {
          "date": "09/29/2023_10/01/2023",
          "spotsAvailable": 0,
          "lastUpdated": "6/9/2023 4:15:51 PM"
        },
        {
          "date": "10/06/2023_10/08/2023",
          "spotsAvailable": 0,
          "lastUpdated": "6/9/2023 4:15:59 PM"
        },
        {
          "date": "10/13/2023_10/15/2023",
          "spotsAvailable": 0,
          "lastUpdated": "6/9/2023 4:16:06 PM"
        },
        {
          "date": "10/20/2023_10/22/2023",
          "spotsAvailable": 0,
          "lastUpdated": "6/9/2023 4:16:13 PM"
        },
        {
          "date": "10/27/2023_10/29/2023",
          "spotsAvailable": 0,
          "lastUpdated": "6/9/2023 4:16:20 PM"
        },
        {
          "date": "11/03/2023_11/05/2023",
          "spotsAvailable": 0,
          "lastUpdated": "6/9/2023 4:16:27 PM"
        },
        {
          "date": "11/10/2023_11/12/2023",
          "spotsAvailable": 0,
          "lastUpdated": "6/9/2023 4:16:34 PM"
        },
        {
          "date": "11/17/2023_11/19/2023",
          "spotsAvailable": 0,
          "lastUpdated": "6/9/2023 4:16:42 PM"
        },
        {
          "date": "11/24/2023_11/26/2023",
          "spotsAvailable": 0,
          "lastUpdated": "6/9/2023 4:16:49 PM"
        },
        {
          "date": "12/01/2023_12/03/2023",
          "spotsAvailable": 0,
          "lastUpdated": "6/9/2023 4:16:56 PM"
        },
        {
          "date": "12/08/2023_12/10/2023",
          "spotsAvailable": 0,
          "lastUpdated": "6/9/2023 4:17:03 PM"
        }
      ]
    },
    {
      "campground": "henry_cowell",
      "dates": [
        {
          "date": "04/28/2023_04/30/2023",
          "spotsAvailable": 0,
          "lastUpdated": "4/26/2023 2:33:43 PM"
        },
        {
          "date": "05/05/2023_05/07/2023",
          "spotsAvailable": 0,
          "lastUpdated": "5/4/2023 9:11:12 PM"
        },
        {
          "date": "05/12/2023_05/14/2023",
          "spotsAvailable": 0,
          "lastUpdated": "5/11/2023 6:20:28 PM"
        },
        {
          "date": "05/19/2023_05/21/2023",
          "spotsAvailable": 0,
          "lastUpdated": "5/18/2023 1:21:01 AM"
        },
        {
          "date": "05/26/2023_05/28/2023",
          "spotsAvailable": 0,
          "lastUpdated": "5/25/2023 11:20:54 PM"
        },
        {
          "date": "06/02/2023_06/04/2023",
          "spotsAvailable": 0,
          "lastUpdated": "6/2/2023 12:12:59 AM"
        },
        {
          "date": "06/09/2023_06/11/2023",
          "spotsAvailable": 0,
          "lastUpdated": "6/9/2023 12:17:33 AM"
        },
        {
          "date": "06/16/2023_06/18/2023",
          "spotsAvailable": 0,
          "lastUpdated": "6/9/2023 5:14:57 PM"
        },
        {
          "date": "06/23/2023_06/25/2023",
          "spotsAvailable": 0,
          "lastUpdated": "6/9/2023 5:15:05 PM"
        },
        {
          "date": "06/30/2023_07/02/2023",
          "spotsAvailable": 0,
          "lastUpdated": "6/9/2023 5:15:12 PM"
        },
        {
          "date": "07/07/2023_07/09/2023",
          "spotsAvailable": 0,
          "lastUpdated": "6/9/2023 5:15:20 PM"
        },
        {
          "date": "07/14/2023_07/16/2023",
          "spotsAvailable": 0,
          "lastUpdated": "6/9/2023 5:15:27 PM"
        },
        {
          "date": "07/21/2023_07/23/2023",
          "spotsAvailable": 0,
          "lastUpdated": "6/9/2023 5:15:36 PM"
        },
        {
          "date": "07/28/2023_07/30/2023",
          "spotsAvailable": 0,
          "lastUpdated": "6/9/2023 5:15:44 PM"
        },
        {
          "date": "08/04/2023_08/06/2023",
          "spotsAvailable": 0,
          "lastUpdated": "6/9/2023 5:15:51 PM"
        },
        {
          "date": "08/11/2023_08/13/2023",
          "spotsAvailable": 0,
          "lastUpdated": "6/9/2023 5:15:58 PM"
        },
        {
          "date": "08/18/2023_08/20/2023",
          "spotsAvailable": 0,
          "lastUpdated": "6/9/2023 5:16:06 PM"
        },
        {
          "date": "08/25/2023_08/27/2023",
          "spotsAvailable": 0,
          "lastUpdated": "6/9/2023 5:16:13 PM"
        },
        {
          "date": "09/01/2023_09/03/2023",
          "spotsAvailable": 0,
          "lastUpdated": "6/9/2023 5:16:20 PM"
        },
        {
          "date": "09/08/2023_09/10/2023",
          "spotsAvailable": 0,
          "lastUpdated": "6/9/2023 5:16:27 PM"
        },
        {
          "date": "09/15/2023_09/17/2023",
          "spotsAvailable": 0,
          "lastUpdated": "6/9/2023 5:16:34 PM"
        },
        {
          "date": "09/22/2023_09/24/2023",
          "spotsAvailable": 0,
          "lastUpdated": "6/9/2023 5:16:42 PM"
        },
        {
          "date": "09/29/2023_10/01/2023",
          "spotsAvailable": 0,
          "lastUpdated": "6/9/2023 5:16:49 PM"
        },
        {
          "date": "10/06/2023_10/08/2023",
          "spotsAvailable": 0,
          "lastUpdated": "6/9/2023 5:16:56 PM"
        },
        {
          "date": "10/13/2023_10/15/2023",
          "spotsAvailable": 0,
          "lastUpdated": "6/9/2023 5:17:03 PM"
        },
        {
          "date": "10/20/2023_10/22/2023",
          "spotsAvailable": 0,
          "lastUpdated": "6/9/2023 5:17:11 PM"
        },
        {
          "date": "10/27/2023_10/29/2023",
          "spotsAvailable": 0,
          "lastUpdated": "6/9/2023 5:17:19 PM"
        },
        {
          "date": "11/03/2023_11/05/2023",
          "spotsAvailable": 0,
          "lastUpdated": "6/9/2023 5:17:26 PM"
        },
        {
          "date": "11/10/2023_11/12/2023",
          "spotsAvailable": 0,
          "lastUpdated": "6/9/2023 5:17:33 PM"
        },
        {
          "date": "11/17/2023_11/19/2023",
          "spotsAvailable": 0,
          "lastUpdated": "6/9/2023 5:17:41 PM"
        },
        {
          "date": "11/24/2023_11/26/2023",
          "spotsAvailable": 0,
          "lastUpdated": "6/9/2023 5:17:48 PM"
        },
        {
          "date": "12/01/2023_12/03/2023",
          "spotsAvailable": 0,
          "lastUpdated": "6/9/2023 5:17:55 PM"
        },
        {
          "date": "12/08/2023_12/10/2023",
          "spotsAvailable": 0,
          "lastUpdated": "6/9/2023 5:18:03 PM"
        }
      ]
    },
    {
      "campground": "leo_carillo",
      "dates": [
        {
          "date": "05/05/2023_05/07/2023",
          "spotsAvailable": 0,
          "lastUpdated": "5/4/2023 11:10:54 PM"
        },
        {
          "date": "05/12/2023_05/14/2023",
          "spotsAvailable": 0,
          "lastUpdated": "5/12/2023 12:10:50 AM"
        },
        {
          "date": "05/19/2023_05/21/2023",
          "spotsAvailable": 0,
          "lastUpdated": "5/18/2023 1:10:57 AM"
        },
        {
          "date": "05/26/2023_05/28/2023",
          "spotsAvailable": 0,
          "lastUpdated": "5/26/2023 12:10:55 AM"
        },
        {
          "date": "06/02/2023_06/04/2023",
          "spotsAvailable": 0,
          "lastUpdated": "6/1/2023 11:07:22 PM"
        },
        {
          "date": "06/09/2023_06/11/2023",
          "spotsAvailable": 0,
          "lastUpdated": "6/9/2023 12:07:29 AM"
        },
        {
          "date": "06/16/2023_06/18/2023",
          "spotsAvailable": 0,
          "lastUpdated": "6/9/2023 5:08:04 PM"
        },
        {
          "date": "06/23/2023_06/25/2023",
          "spotsAvailable": 0,
          "lastUpdated": "6/9/2023 5:08:12 PM"
        },
        {
          "date": "06/30/2023_07/02/2023",
          "spotsAvailable": 0,
          "lastUpdated": "6/9/2023 5:08:21 PM"
        },
        {
          "date": "07/07/2023_07/09/2023",
          "spotsAvailable": 0,
          "lastUpdated": "6/9/2023 5:08:29 PM"
        },
        {
          "date": "07/14/2023_07/16/2023",
          "spotsAvailable": 0,
          "lastUpdated": "6/9/2023 5:08:36 PM"
        },
        {
          "date": "07/21/2023_07/23/2023",
          "spotsAvailable": 0,
          "lastUpdated": "6/9/2023 5:08:43 PM"
        },
        {
          "date": "07/28/2023_07/30/2023",
          "spotsAvailable": 0,
          "lastUpdated": "6/9/2023 5:08:51 PM"
        },
        {
          "date": "08/04/2023_08/06/2023",
          "spotsAvailable": 0,
          "lastUpdated": "6/9/2023 5:08:59 PM"
        },
        {
          "date": "08/11/2023_08/13/2023",
          "spotsAvailable": 0,
          "lastUpdated": "6/9/2023 5:09:07 PM"
        },
        {
          "date": "08/18/2023_08/20/2023",
          "spotsAvailable": 0,
          "lastUpdated": "6/9/2023 5:09:15 PM"
        },
        {
          "date": "08/25/2023_08/27/2023",
          "spotsAvailable": 0,
          "lastUpdated": "6/9/2023 5:09:23 PM"
        },
        {
          "date": "09/01/2023_09/03/2023",
          "spotsAvailable": 0,
          "lastUpdated": "6/9/2023 5:09:30 PM"
        },
        {
          "date": "09/08/2023_09/10/2023",
          "spotsAvailable": 0,
          "lastUpdated": "6/9/2023 5:09:39 PM"
        },
        {
          "date": "09/15/2023_09/17/2023",
          "spotsAvailable": 0,
          "lastUpdated": "6/9/2023 5:09:48 PM"
        },
        {
          "date": "09/22/2023_09/24/2023",
          "spotsAvailable": 0,
          "lastUpdated": "6/9/2023 5:09:57 PM"
        },
        {
          "date": "09/29/2023_10/01/2023",
          "spotsAvailable": 0,
          "lastUpdated": "6/9/2023 5:10:05 PM"
        },
        {
          "date": "10/06/2023_10/08/2023",
          "spotsAvailable": 0,
          "lastUpdated": "6/9/2023 5:10:12 PM"
        },
        {
          "date": "10/13/2023_10/15/2023",
          "spotsAvailable": 0,
          "lastUpdated": "6/9/2023 5:10:20 PM"
        },
        {
          "date": "10/20/2023_10/22/2023",
          "spotsAvailable": 0,
          "lastUpdated": "6/9/2023 5:10:28 PM"
        },
        {
          "date": "10/27/2023_10/29/2023",
          "spotsAvailable": 0,
          "lastUpdated": "6/9/2023 5:10:36 PM"
        },
        {
          "date": "11/03/2023_11/05/2023",
          "spotsAvailable": 0,
          "lastUpdated": "6/9/2023 5:10:43 PM"
        },
        {
          "date": "11/10/2023_11/12/2023",
          "spotsAvailable": 0,
          "lastUpdated": "6/9/2023 5:10:51 PM"
        },
        {
          "date": "11/17/2023_11/19/2023",
          "spotsAvailable": 22,
          "lastUpdated": "6/9/2023 5:10:58 PM"
        },
        {
          "date": "11/24/2023_11/26/2023",
          "spotsAvailable": 1,
          "lastUpdated": "6/9/2023 5:11:05 PM"
        },
        {
          "date": "12/01/2023_12/03/2023",
          "spotsAvailable": 1,
          "lastUpdated": "6/9/2023 5:11:13 PM"
        },
        {
          "date": "12/08/2023_12/10/2023",
          "spotsAvailable": 1,
          "lastUpdated": "6/9/2023 5:11:20 PM"
        }
      ]
    },
    {
      "campground": "south_carlsbad_sb",
      "dates": [
        {
          "date": "05/05/2023_05/07/2023",
          "spotsAvailable": 0,
          "lastUpdated": "5/4/2023 11:17:34 PM"
        },
        {
          "date": "05/12/2023_05/14/2023",
          "spotsAvailable": 0,
          "lastUpdated": "5/11/2023 7:05:16 PM"
        },
        {
          "date": "05/19/2023_05/21/2023",
          "spotsAvailable": 0,
          "lastUpdated": "5/18/2023 1:17:41 AM"
        },
        {
          "date": "05/26/2023_05/28/2023",
          "spotsAvailable": 0,
          "lastUpdated": "5/26/2023 12:17:33 AM"
        },
        {
          "date": "06/02/2023_06/04/2023",
          "spotsAvailable": 0,
          "lastUpdated": "6/2/2023 12:11:32 AM"
        },
        {
          "date": "06/09/2023_06/11/2023",
          "spotsAvailable": 0,
          "lastUpdated": "6/9/2023 12:14:14 AM"
        },
        {
          "date": "06/16/2023_06/18/2023",
          "spotsAvailable": 0,
          "lastUpdated": "6/9/2023 5:11:35 PM"
        },
        {
          "date": "06/23/2023_06/25/2023",
          "spotsAvailable": 0,
          "lastUpdated": "6/9/2023 5:11:43 PM"
        },
        {
          "date": "06/30/2023_07/02/2023",
          "spotsAvailable": 0,
          "lastUpdated": "6/9/2023 5:11:50 PM"
        },
        {
          "date": "07/07/2023_07/09/2023",
          "spotsAvailable": 0,
          "lastUpdated": "6/9/2023 5:11:59 PM"
        },
        {
          "date": "07/14/2023_07/16/2023",
          "spotsAvailable": 0,
          "lastUpdated": "6/9/2023 5:12:06 PM"
        },
        {
          "date": "07/21/2023_07/23/2023",
          "spotsAvailable": 0,
          "lastUpdated": "6/9/2023 5:12:14 PM"
        },
        {
          "date": "07/28/2023_07/30/2023",
          "spotsAvailable": 0,
          "lastUpdated": "6/9/2023 5:12:22 PM"
        },
        {
          "date": "08/04/2023_08/06/2023",
          "spotsAvailable": 0,
          "lastUpdated": "6/9/2023 5:12:30 PM"
        },
        {
          "date": "08/11/2023_08/13/2023",
          "spotsAvailable": 0,
          "lastUpdated": "6/9/2023 5:12:37 PM"
        },
        {
          "date": "08/18/2023_08/20/2023",
          "spotsAvailable": 0,
          "lastUpdated": "6/9/2023 5:12:44 PM"
        },
        {
          "date": "08/25/2023_08/27/2023",
          "spotsAvailable": 0,
          "lastUpdated": "6/9/2023 5:12:52 PM"
        },
        {
          "date": "09/01/2023_09/03/2023",
          "spotsAvailable": 0,
          "lastUpdated": "6/9/2023 5:12:59 PM"
        },
        {
          "date": "09/08/2023_09/10/2023",
          "spotsAvailable": 0,
          "lastUpdated": "6/9/2023 5:13:07 PM"
        },
        {
          "date": "09/15/2023_09/17/2023",
          "spotsAvailable": 0,
          "lastUpdated": "6/9/2023 5:13:16 PM"
        },
        {
          "date": "09/22/2023_09/24/2023",
          "spotsAvailable": 0,
          "lastUpdated": "6/9/2023 5:13:24 PM"
        },
        {
          "date": "09/29/2023_10/01/2023",
          "spotsAvailable": 0,
          "lastUpdated": "6/9/2023 5:13:32 PM"
        },
        {
          "date": "10/06/2023_10/08/2023",
          "spotsAvailable": 0,
          "lastUpdated": "6/9/2023 5:13:39 PM"
        },
        {
          "date": "10/13/2023_10/15/2023",
          "spotsAvailable": 0,
          "lastUpdated": "6/9/2023 5:13:46 PM"
        },
        {
          "date": "10/20/2023_10/22/2023",
          "spotsAvailable": 0,
          "lastUpdated": "6/9/2023 5:13:54 PM"
        },
        {
          "date": "10/27/2023_10/29/2023",
          "spotsAvailable": 0,
          "lastUpdated": "6/9/2023 5:14:01 PM"
        },
        {
          "date": "11/03/2023_11/05/2023",
          "spotsAvailable": 0,
          "lastUpdated": "6/9/2023 5:14:08 PM"
        },
        {
          "date": "11/10/2023_11/12/2023",
          "spotsAvailable": 0,
          "lastUpdated": "6/9/2023 5:14:15 PM"
        },
        {
          "date": "11/17/2023_11/19/2023",
          "spotsAvailable": 0,
          "lastUpdated": "6/9/2023 5:14:23 PM"
        },
        {
          "date": "11/24/2023_11/26/2023",
          "spotsAvailable": 0,
          "lastUpdated": "6/9/2023 5:14:30 PM"
        },
        {
          "date": "12/01/2023_12/03/2023",
          "spotsAvailable": 0,
          "lastUpdated": "6/9/2023 5:14:38 PM"
        },
        {
          "date": "12/08/2023_12/10/2023",
          "spotsAvailable": 0,
          "lastUpdated": "6/9/2023 5:14:45 PM"
        }
      ]
    }
  ]
}